<?xml version="1.0" encoding="ISO-8859-1"?>
<modeling>
 <generator>
  <i name="program" type="string">vasp </i>
  <i name="version" type="string">5.4.4.18Apr17-6-g9f103f2a35  </i>
  <i name="subversion" type="string">(build Sep 03 2018 23:53:05) complex            parallel </i>
  <i name="platform" type="string">LinuxIFC </i>
  <i name="date" type="string">2021 11 30 </i>
  <i name="time" type="string">15:12:11 </i>
 </generator>
 <incar>
  <i type="string" name="SYSTEM"> 6_Pd100_top_free_z(O)</i>
  <i type="int" name="ISTART">     0</i>
  <i type="string" name="PREC">normal   			! encut=max(enmax), ngx,y,z</i>
  <i type="string" name="ALGO"> Fast     			! Mix RMM-DIIS and Dav</i>
  <i type="logical" name="ADDGRID"> F  </i>
  <i type="int" name="ISPIN">     1</i>
  <i type="int" name="ICHARG">     2</i>
  <i type="int" name="NELM">   100</i>
  <i type="int" name="NELMIN">     6</i>
  <i type="int" name="IBRION">     2</i>
  <i name="EDIFF">      0.00010000</i>
  <i name="EDIFFG">     -0.05000000</i>
  <i type="int" name="NSW">     0</i>
  <i type="int" name="ISIF">     2</i>
  <i type="int" name="ISYM">     2</i>
  <i name="ENCUT">    400.00000000</i>
  <i type="string" name="LREAL"> Auto     			! Auto or A projection done</i>
  <i type="int" name="ISMEAR">     2</i>
  <i name="SIGMA">      0.20000000</i>
  <i type="logical" name="LWAVE"> F  </i>
  <i type="logical" name="LCHARG"> F  </i>
  <v type="int" name="KPOINT_BSE">    -1     0     0     0</v>
  <i type="int" name="MAXMEM"> 10000</i>
  <i type="int" name="NELM">   100</i>
  <i type="string" name="GGA"> RP         			! Revised PBE</i>
 </incar>
 <structure name="primitive_cell" >
  <crystal>
   <varray name="basis" >
    <v>      30.00000000       0.00000000       0.00000000 </v>
    <v>       0.00000000      30.00000000       0.00000000 </v>
    <v>       0.00000000       0.00000000      30.00000000 </v>
   </varray>
   <i name="volume">  27000.00000000 </i>
   <varray name="rec_basis" >
    <v>       0.03333333       0.00000000       0.00000000 </v>
    <v>       0.00000000       0.03333333       0.00000000 </v>
    <v>       0.00000000       0.00000000       0.03333333 </v>
   </varray>
  </crystal>
  <varray name="positions" >
   <v>       0.44576020       0.32826710       0.41691983 </v>
   <v>      -0.44576020       0.32826710       0.41691983 </v>
   <v>      -0.50000000       0.38250690       0.34021317 </v>
   <v>      -0.50000000       0.27609440      -0.50000000 </v>
   <v>       0.38804720       0.38804720       0.34167483 </v>
   <v>      -0.50000000       0.38416601      -0.50000000 </v>
   <v>       0.44208300       0.44208300       0.41809300 </v>
   <v>       0.38317830       0.38317830      -0.50000000 </v>
   <v>      -0.44208300       0.44208300       0.41809300 </v>
   <v>       0.44576020       0.32826710      -0.41691977 </v>
   <v>       0.32826705       0.44576024       0.41691983 </v>
   <v>      -0.38804720       0.38804720       0.34167483 </v>
   <v>      -0.38317830       0.38317830      -0.50000000 </v>
   <v>      -0.50000000      -0.50000000       0.33478917 </v>
   <v>      -0.50000000      -0.50000000      -0.50000000 </v>
   <v>      -0.44576020       0.32826710      -0.41691977 </v>
   <v>       0.38250685      -0.49999995       0.34021317 </v>
   <v>       0.44208300       0.44208300      -0.41809297 </v>
   <v>       0.38416599      -0.49999998      -0.50000000 </v>
   <v>      -0.44208300       0.44208300      -0.41809297 </v>
   <v>       0.44208298      -0.44208298       0.41809300 </v>
   <v>       0.32826705       0.44576024      -0.41691977 </v>
   <v>       0.26979247       0.46353870      -0.45932153 </v>
   <v>      -0.50000000       0.38250690      -0.34021320 </v>
   <v>       0.32826712      -0.44576022       0.41691983 </v>
   <v>      -0.38250685      -0.49999995       0.34021317 </v>
   <v>      -0.32826705       0.44576024       0.41691983 </v>
   <v>       0.27609443       0.49999998      -0.50000000 </v>
   <v>       0.38804720       0.38804720      -0.34167487 </v>
   <v>      -0.38416599      -0.49999998      -0.50000000 </v>
   <v>      -0.44208298      -0.44208298       0.41809300 </v>
   <v>       0.23320840       0.45774437      -0.45285700 </v>
   <v>       0.44208298      -0.44208298      -0.41809297 </v>
   <v>      -0.38804720       0.38804720      -0.34167487 </v>
   <v>       0.38804722      -0.38804722       0.34167483 </v>
   <v>       0.38250685      -0.49999995      -0.34021320 </v>
   <v>       0.32826712      -0.44576022      -0.41691977 </v>
   <v>      -0.32826705       0.44576024      -0.41691977 </v>
   <v>       0.50000000      -0.38250681       0.34021317 </v>
   <v>      -0.50000000      -0.38416596      -0.50000000 </v>
   <v>      -0.44208298      -0.44208298      -0.41809297 </v>
   <v>      -0.50000000      -0.50000000      -0.33478913 </v>
   <v>       0.38317828      -0.38317828      -0.50000000 </v>
   <v>      -0.32826712      -0.44576022       0.41691983 </v>
   <v>      -0.27609443       0.49999998      -0.50000000 </v>
   <v>      -0.38804722      -0.38804722       0.34167483 </v>
   <v>      -0.38250685      -0.49999995      -0.34021320 </v>
   <v>       0.44576027      -0.32826707       0.41691983 </v>
   <v>      -0.38317828      -0.38317828      -0.50000000 </v>
   <v>      -0.32826712      -0.44576022      -0.41691977 </v>
   <v>      -0.44576027      -0.32826707       0.41691983 </v>
   <v>       0.38804722      -0.38804722      -0.34167487 </v>
   <v>      -0.50000000      -0.38250681      -0.34021320 </v>
   <v>       0.44576027      -0.32826707      -0.41691977 </v>
   <v>      -0.44576027      -0.32826707      -0.41691977 </v>
   <v>      -0.50000000      -0.27609445       0.50000000 </v>
   <v>      -0.38804722      -0.38804722      -0.34167487 </v>
  </varray>
 </structure>
 <varray name="primitive_index" >
  <v type="int" >        1 </v>
  <v type="int" >        3 </v>
  <v type="int" >        5 </v>
  <v type="int" >        7 </v>
  <v type="int" >       15 </v>
  <v type="int" >       29 </v>
  <v type="int" >       28 </v>
  <v type="int" >       34 </v>
  <v type="int" >       21 </v>
  <v type="int" >       19 </v>
  <v type="int" >       22 </v>
  <v type="int" >       11 </v>
  <v type="int" >       36 </v>
  <v type="int" >       38 </v>
  <v type="int" >       52 </v>
  <v type="int" >       24 </v>
  <v type="int" >       32 </v>
  <v type="int" >       44 </v>
  <v type="int" >       48 </v>
  <v type="int" >       42 </v>
  <v type="int" >       43 </v>
  <v type="int" >       40 </v>
  <v type="int" >       56 </v>
  <v type="int" >        6 </v>
  <v type="int" >        4 </v>
  <v type="int" >       30 </v>
  <v type="int" >       26 </v>
  <v type="int" >        8 </v>
  <v type="int" >       16 </v>
  <v type="int" >       49 </v>
  <v type="int" >       47 </v>
  <v type="int" >       57 </v>
  <v type="int" >       53 </v>
  <v type="int" >       12 </v>
  <v type="int" >       13 </v>
  <v type="int" >       33 </v>
  <v type="int" >       25 </v>
  <v type="int" >       45 </v>
  <v type="int" >       50 </v>
  <v type="int" >       55 </v>
  <v type="int" >       54 </v>
  <v type="int" >       39 </v>
  <v type="int" >       37 </v>
  <v type="int" >        2 </v>
  <v type="int" >        9 </v>
  <v type="int" >       17 </v>
  <v type="int" >       31 </v>
  <v type="int" >       27 </v>
  <v type="int" >       35 </v>
  <v type="int" >       20 </v>
  <v type="int" >       23 </v>
  <v type="int" >       14 </v>
  <v type="int" >       51 </v>
  <v type="int" >       46 </v>
  <v type="int" >       41 </v>
  <v type="int" >       10 </v>
  <v type="int" >       18 </v>
 </varray>
 <kpoints>
  <generation param="Monkhorst-Pack">
   <v type="int" name="divisions">       1        1        1 </v>
   <v name="usershift">      0.00000000       0.00000000       0.00000000 </v>
   <v name="genvec1">      1.00000000       0.00000000       0.00000000 </v>
   <v name="genvec2">      0.00000000       1.00000000       0.00000000 </v>
   <v name="genvec3">      0.00000000       0.00000000       1.00000000 </v>
   <v name="shift">      0.00000000       0.00000000       0.00000000 </v>
  </generation>
  <varray name="kpointlist" >
   <v>       0.00000000       0.00000000       0.00000000 </v>
  </varray>
  <varray name="weights" >
   <v>       1.00000000 </v>
  </varray>
 </kpoints>
 <parameters>
  <separator name="general" >
   <i type="string" name="SYSTEM">6_Pd100_top_free_z(O)</i>
   <i type="logical" name="LCOMPAT"> F  </i>
  </separator>
  <separator name="electronic" >
   <i type="string" name="PREC">normal</i>
   <i name="ENMAX">    400.00000000</i>
   <i name="ENAUG">    644.87300000</i>
   <i name="EDIFF">      0.00010000</i>
   <i type="int" name="IALGO">    68</i>
   <i type="int" name="IWAVPR">    10</i>
   <i type="int" name="NBANDS">   336</i>
   <i name="NELECT">    560.00000000</i>
   <i type="int" name="TURBO">     0</i>
   <i type="int" name="IRESTART">     0</i>
   <i type="int" name="NREBOOT">     0</i>
   <i type="int" name="NMIN">     0</i>
   <i name="EREF">      0.00000000</i>
   <separator name="electronic smearing" >
    <i type="int" name="ISMEAR">     2</i>
    <i name="SIGMA">      0.20000000</i>
    <i name="KSPACING">      0.50000000</i>
    <i type="logical" name="KGAMMA"> T  </i>
   </separator>
   <separator name="electronic projectors" >
    <i type="logical" name="LREAL"> T  </i>
    <v name="ROPT">     -0.00050000     -0.00050000     -0.00050000</v>
    <i type="int" name="LMAXPAW">  -100</i>
    <i type="int" name="LMAXMIX">     2</i>
    <i type="logical" name="NLSPLINE"> F  </i>
   </separator>
   <separator name="electronic startup" >
    <i type="int" name="ISTART">     0</i>
    <i type="int" name="ICHARG">     2</i>
    <i type="int" name="INIWAV">     1</i>
   </separator>
   <separator name="electronic spin" >
    <i type="int" name="ISPIN">     1</i>
    <i type="logical" name="LNONCOLLINEAR"> F  </i>
    <v name="MAGMOM">      1.00000000      1.00000000      1.00000000      1.00000000      1.00000000      1.00000000      1.00000000      1.00000000      1.00000000      1.00000000      1.00000000      1.00000000      1.00000000      1.00000000      1.00000000      1.00000000      1.00000000      1.00000000      1.00000000      1.00000000
      1.00000000      1.00000000      1.00000000      1.00000000      1.00000000      1.00000000      1.00000000      1.00000000      1.00000000      1.00000000      1.00000000      1.00000000      1.00000000      1.00000000      1.00000000      1.00000000      1.00000000      1.00000000      1.00000000      1.00000000
      1.00000000      1.00000000      1.00000000      1.00000000      1.00000000      1.00000000      1.00000000      1.00000000      1.00000000      1.00000000      1.00000000      1.00000000      1.00000000      1.00000000      1.00000000      1.00000000      1.00000000</v>
    <i name="NUPDOWN">     -1.00000000</i>
    <i type="logical" name="LSORBIT"> F  </i>
    <v name="SAXIS">      0.00000000      0.00000000      1.00000000</v>
    <i type="logical" name="LSPIRAL"> F  </i>
    <v name="QSPIRAL">      0.00000000      0.00000000      0.00000000</v>
    <i type="logical" name="LZEROZ"> F  </i>
   </separator>
   <separator name="electronic exchange-correlation" >
    <i type="logical" name="LASPH"> F  </i>
    <i type="logical" name="LMETAGGA"> F  </i>
   </separator>
   <separator name="electronic convergence" >
    <i type="int" name="NELM">   100</i>
    <i type="int" name="NELMDL">    -5</i>
    <i type="int" name="NELMIN">     6</i>
    <i name="ENINI">    400.00000000</i>
    <separator name="electronic convergence detail" >
     <i type="logical" name="LDIAG"> T  </i>
     <i type="logical" name="LSUBROT"> F  </i>
     <i name="WEIMIN">      0.00000000</i>
     <i name="EBREAK">      0.00000007</i>
     <i name="DEPER">      0.30000000</i>
     <i type="int" name="NRMM">     4</i>
     <i name="TIME">      0.40000000</i>
    </separator>
   </separator>
   <separator name="electronic mixer" >
    <i name="AMIX">      0.40000000</i>
    <i name="BMIX">      1.00000000</i>
    <i name="AMIN">      0.10000000</i>
    <i name="AMIX_MAG">      1.60000000</i>
    <i name="BMIX_MAG">      1.00000000</i>
    <separator name="electronic mixer details" >
     <i type="int" name="IMIX">     4</i>
     <i type="logical" name="MIXFIRST"> F  </i>
     <i type="int" name="MAXMIX">   -45</i>
     <i name="WC">    100.00000000</i>
     <i type="int" name="INIMIX">     1</i>
     <i type="int" name="MIXPRE">     1</i>
     <i type="int" name="MREMOVE">     5</i>
    </separator>
   </separator>
   <separator name="electronic dipolcorrection" >
    <i type="logical" name="LDIPOL"> F  </i>
    <i type="logical" name="LMONO"> F  </i>
    <i type="int" name="IDIPOL">     0</i>
    <i name="EPSILON">      1.00000000</i>
    <v name="DIPOL">   -100.00000000   -100.00000000   -100.00000000</v>
    <i name="EFIELD">      0.00000000</i>
   </separator>
  </separator>
  <separator name="grids" >
   <i type="int" name="NGX">   150</i>
   <i type="int" name="NGY">   150</i>
   <i type="int" name="NGZ">   150</i>
   <i type="int" name="NGXF">   300</i>
   <i type="int" name="NGYF">   300</i>
   <i type="int" name="NGZF">   300</i>
   <i type="logical" name="ADDGRID"> F  </i>
  </separator>
  <separator name="ionic" >
   <i type="int" name="NSW">     0</i>
   <i type="int" name="IBRION">    -1</i>
   <i type="int" name="MDALGO">     0</i>
   <i type="int" name="ISIF">     2</i>
   <i name="PSTRESS">      0.00000000</i>
   <i name="EDIFFG">     -0.05000000</i>
   <i type="int" name="NFREE">     1</i>
   <i name="POTIM">      0.50000000</i>
   <i name="SMASS">     -3.00000000</i>
   <i name="SCALEE">      1.00000000</i>
  </separator>
  <separator name="ionic md" >
   <i name="TEBEG">      0.00010000</i>
   <i name="TEEND">      0.00010000</i>
   <i type="int" name="NBLOCK">     1</i>
   <i type="int" name="KBLOCK">     1</i>
   <i type="int" name="NPACO">   256</i>
   <i name="APACO">     16.00000000</i>
  </separator>
  <separator name="symmetry" >
   <i type="int" name="ISYM">     2</i>
   <i name="SYMPREC">      0.00001000</i>
  </separator>
  <separator name="dos" >
   <i type="int" name="LORBIT">     0</i>
   <v name="RWIGS">     -1.00000000     -1.00000000     -1.00000000</v>
   <i type="int" name="NEDOS">   301</i>
   <i name="EMIN">     10.00000000</i>
   <i name="EMAX">    -10.00000000</i>
   <i name="EFERMI">      0.00000000</i>
  </separator>
  <separator name="writing" >
   <i type="int" name="NWRITE">     2</i>
   <i type="logical" name="LWAVE"> F  </i>
   <i type="logical" name="LDOWNSAMPLE"> F  </i>
   <i type="logical" name="LCHARG"> F  </i>
   <i type="logical" name="LPARD"> F  </i>
   <i type="logical" name="LVTOT"> F  </i>
   <i type="logical" name="LVHAR"> F  </i>
   <i type="logical" name="LELF"> F  </i>
   <i type="logical" name="LOPTICS"> F  </i>
   <v name="STM">      0.00000000      0.00000000      0.00000000      0.00000000      0.00000000      0.00000000      0.00000000</v>
  </separator>
  <separator name="performance" >
   <i type="int" name="NPAR">     1</i>
   <i type="int" name="NSIM">     4</i>
   <i type="int" name="NBLK">    -1</i>
   <i type="logical" name="LPLANE"> T  </i>
   <i type="logical" name="LSCALAPACK"> T  </i>
   <i type="logical" name="LSCAAWARE"> F  </i>
   <i type="logical" name="LSCALU"> F  </i>
   <i type="logical" name="LASYNC"> F  </i>
   <i type="logical" name="LORBITALREAL"> F  </i>
  </separator>
  <separator name="miscellaneous" >
   <i type="int" name="IDIOT">     3</i>
   <i type="int" name="ISPECIAL">     0</i>
   <i type="logical" name="LMUSIC"> F  </i>
   <v name="POMASS">    106.42000000     12.01100000     16.00000000</v>
   <v name="DARWINR">      0.00000000      0.00000000      0.00000000</v>
   <v name="DARWINV">      1.00000000      1.00000000      1.00000000</v>
   <i type="logical" name="LCORR"> T  </i>
  </separator>
  <i type="logical" name="GGA_COMPAT"> T  </i>
  <i type="logical" name="LBERRY"> F  </i>
  <i type="int" name="ICORELEVEL">     0</i>
  <i type="logical" name="LDAU"> F  </i>
  <i type="int" name="I_CONSTRAINED_M">     0</i>
  <separator name="electronic exchange-correlation" >
   <i type="string" name="GGA">RP</i>
   <i type="int" name="VOSKOWN">     0</i>
   <i type="logical" name="LHFCALC"> F  </i>
   <i type="string" name="PRECFOCK"></i>
   <i type="logical" name="LSYMGRAD"> F  </i>
   <i type="logical" name="LHFONE"> F  </i>
   <i type="logical" name="LRHFCALC"> F  </i>
   <i type="logical" name="LTHOMAS"> F  </i>
   <i type="logical" name="LMODELHF"> F  </i>
   <i name="ENCUT4O">     -1.00000000</i>
   <i type="int" name="EXXOEP">     0</i>
   <i type="int" name="FOURORBIT">     0</i>
   <i name="AEXX">      0.00000000</i>
   <i name="HFALPHA">      0.00000000</i>
   <i name="MCALPHA">      0.00000000</i>
   <i name="ALDAX">      1.00000000</i>
   <i name="AGGAX">      1.00000000</i>
   <i name="ALDAC">      1.00000000</i>
   <i name="AGGAC">      1.00000000</i>
   <i type="int" name="NKREDX">     1</i>
   <i type="int" name="NKREDY">     1</i>
   <i type="int" name="NKREDZ">     1</i>
   <i type="logical" name="SHIFTRED"> F  </i>
   <i type="logical" name="ODDONLY"> F  </i>
   <i type="logical" name="EVENONLY"> F  </i>
   <i type="int" name="LMAXFOCK">     0</i>
   <i type="int" name="NMAXFOCKAE">     0</i>
   <i type="logical" name="LFOCKAEDFT"> F  </i>
   <i name="HFSCREEN">      0.00000000</i>
   <i name="HFSCREENC">      0.00000000</i>
   <i type="int" name="NBANDSGWLOW">     0</i>
  </separator>
  <separator name="vdW DFT" >
   <i type="logical" name="LUSE_VDW"> F  </i>
   <i name="Zab_VDW">     -0.84910000</i>
   <i name="PARAM1">      0.12340000</i>
   <i name="PARAM2">      1.00000000</i>
   <i name="PARAM3">      0.00000000</i>
  </separator>
  <separator name="model GW" >
   <i type="int" name="MODEL_GW">     0</i>
   <i name="MODEL_EPS0">    284.21052632</i>
   <i name="MODEL_ALPHA">      1.00000000</i>
  </separator>
  <separator name="linear response parameters" >
   <i type="logical" name="LEPSILON"> F  </i>
   <i type="logical" name="LRPA"> F  </i>
   <i type="logical" name="LNABLA"> F  </i>
   <i type="logical" name="LVEL"> F  </i>
   <i type="int" name="KINTER">     0</i>
   <i name="CSHIFT">      0.10000000</i>
   <i name="OMEGAMAX">     -1.00000000</i>
   <i name="DEG_THRESHOLD">      0.00200000</i>
   <i name="RTIME">     -0.10000000</i>
   <i name="WPLASMAI">      0.00000000</i>
   <v name="DFIELD">      0.00000000      0.00000000      0.00000000</v>
   <v name="WPLASMA">      0.00000000      0.00000000      0.00000000      0.00000000      0.00000000      0.00000000      0.00000000      0.00000000      0.00000000</v>
  </separator>
  <separator name="orbital magnetization" >
   <i type="logical" name="NUCIND"> F  </i>
   <v name="MAGPOS">      0.00000000      0.00000000      0.00000000</v>
   <i type="logical" name="LNICSALL"> T  </i>
   <i type="logical" name="ORBITALMAG"> F  </i>
   <i type="logical" name="LMAGBLOCH"> F  </i>
   <i type="logical" name="LCHIMAG"> F  </i>
   <i type="logical" name="LGAUGE"> T  </i>
   <i type="int" name="MAGATOM">     0</i>
   <v name="MAGDIPOL">      0.00000000      0.00000000      0.00000000</v>
   <v name="AVECCONST">      0.00000000      0.00000000      0.00000000</v>
  </separator>
  <separator name="response functions" >
   <i type="logical" name="LADDER"> F  </i>
   <i type="logical" name="LRPAFORCE"> F  </i>
   <i type="logical" name="LFXC"> F  </i>
   <i type="logical" name="LHARTREE"> T  </i>
   <i type="int" name="IBSE">     0</i>
   <v type="int" name="KPOINT">    -1     0     0     0</v>
   <i type="logical" name="LTCTE"> F  </i>
   <i type="logical" name="LTETE"> F  </i>
   <i type="logical" name="LTRIPLET"> F  </i>
   <i type="logical" name="LFXCEPS"> F  </i>
   <i type="logical" name="LFXHEG"> F  </i>
   <i type="int" name="NATURALO">     2</i>
   <i type="logical" name="L2ORDER"> F  </i>
   <i type="logical" name="LMP2LT"> F  </i>
   <i type="logical" name="LUSEW"> F  </i>
   <i name="ENCUTGW">     -2.00000000</i>
   <i name="ENCUTGWSOFT">     -2.00000000</i>
   <i name="ENCUTLF">     -1.00000000</i>
   <i type="int" name="LMAXMP2">    -1</i>
   <i name="SCISSOR">      0.00000000</i>
   <i type="int" name="NOMEGA">     0</i>
   <i type="int" name="NOMEGAR">     0</i>
   <i type="int" name="NBANDSGW">    -1</i>
   <i type="int" name="NBANDSO">    -1</i>
   <i type="int" name="NBANDSV">    -1</i>
   <i type="int" name="NELM">   100</i>
   <i type="int" name="NELMHF">     1</i>
   <i type="int" name="DIM">     3</i>
   <i type="int" name="ANTIRES">     0</i>
   <i name="OMEGAMAX">    -30.00000000</i>
   <i name="OMEGAMIN">    -30.00000000</i>
   <i name="OMEGATL">   -200.00000000</i>
   <i type="int" name="OMEGAGRID">   140</i>
   <i name="CSHIFT">     -0.10000000</i>
   <i type="logical" name="SELFENERGY"> F  </i>
   <i type="logical" name="LSPECTRAL"> F  </i>
   <i type="logical" name="LSPECTRALGW"> F  </i>
   <i type="logical" name="LSINGLES"> F  </i>
   <i type="logical" name="LFERMIGW"> F  </i>
   <i type="logical" name="ODDONLYGW"> F  </i>
   <i type="logical" name="EVENONLYGW"> F  </i>
   <i type="int" name="NKREDLFX">     1</i>
   <i type="int" name="NKREDLFY">     1</i>
   <i type="int" name="NKREDLFZ">     1</i>
   <i type="int" name="MAXMEM"> 10000</i>
   <i type="int" name="TELESCOPE">     0</i>
   <i type="int" name="TAUPAR">     1</i>
   <i type="int" name="OMEGAPAR">    -1</i>
   <i name="LAMBDA">      1.00000000</i>
  </separator>
  <separator name="External order field" >
   <i name="OFIELD_KAPPA">      0.00000000</i>
   <v name="OFIELD_K">      0.00000000      0.00000000      0.00000000</v>
   <i name="OFIELD_Q6_NEAR">      0.00000000</i>
   <i name="OFIELD_Q6_FAR">      0.00000000</i>
   <i name="OFIELD_A">      0.00000000</i>
  </separator>
 </parameters>
 <atominfo>
  <atoms>      57 </atoms>
  <types>       3 </types>
  <array name="atoms" >
   <dimension dim="1">ion</dimension>
   <field type="string">element</field>
   <field type="int">atomtype</field>
   <set>
    <rc><c>Pd</c><c>   1</c></rc>
    <rc><c>Pd</c><c>   1</c></rc>
    <rc><c>Pd</c><c>   1</c></rc>
    <rc><c>Pd</c><c>   1</c></rc>
    <rc><c>Pd</c><c>   1</c></rc>
    <rc><c>Pd</c><c>   1</c></rc>
    <rc><c>Pd</c><c>   1</c></rc>
    <rc><c>Pd</c><c>   1</c></rc>
    <rc><c>Pd</c><c>   1</c></rc>
    <rc><c>Pd</c><c>   1</c></rc>
    <rc><c>Pd</c><c>   1</c></rc>
    <rc><c>Pd</c><c>   1</c></rc>
    <rc><c>Pd</c><c>   1</c></rc>
    <rc><c>Pd</c><c>   1</c></rc>
    <rc><c>Pd</c><c>   1</c></rc>
    <rc><c>Pd</c><c>   1</c></rc>
    <rc><c>Pd</c><c>   1</c></rc>
    <rc><c>Pd</c><c>   1</c></rc>
    <rc><c>Pd</c><c>   1</c></rc>
    <rc><c>Pd</c><c>   1</c></rc>
    <rc><c>Pd</c><c>   1</c></rc>
    <rc><c>Pd</c><c>   1</c></rc>
    <rc><c>Pd</c><c>   1</c></rc>
    <rc><c>Pd</c><c>   1</c></rc>
    <rc><c>Pd</c><c>   1</c></rc>
    <rc><c>Pd</c><c>   1</c></rc>
    <rc><c>Pd</c><c>   1</c></rc>
    <rc><c>Pd</c><c>   1</c></rc>
    <rc><c>Pd</c><c>   1</c></rc>
    <rc><c>Pd</c><c>   1</c></rc>
    <rc><c>Pd</c><c>   1</c></rc>
    <rc><c>Pd</c><c>   1</c></rc>
    <rc><c>Pd</c><c>   1</c></rc>
    <rc><c>Pd</c><c>   1</c></rc>
    <rc><c>Pd</c><c>   1</c></rc>
    <rc><c>Pd</c><c>   1</c></rc>
    <rc><c>Pd</c><c>   1</c></rc>
    <rc><c>Pd</c><c>   1</c></rc>
    <rc><c>Pd</c><c>   1</c></rc>
    <rc><c>Pd</c><c>   1</c></rc>
    <rc><c>Pd</c><c>   1</c></rc>
    <rc><c>Pd</c><c>   1</c></rc>
    <rc><c>Pd</c><c>   1</c></rc>
    <rc><c>Pd</c><c>   1</c></rc>
    <rc><c>Pd</c><c>   1</c></rc>
    <rc><c>Pd</c><c>   1</c></rc>
    <rc><c>Pd</c><c>   1</c></rc>
    <rc><c>Pd</c><c>   1</c></rc>
    <rc><c>Pd</c><c>   1</c></rc>
    <rc><c>Pd</c><c>   1</c></rc>
    <rc><c>Pd</c><c>   1</c></rc>
    <rc><c>Pd</c><c>   1</c></rc>
    <rc><c>Pd</c><c>   1</c></rc>
    <rc><c>Pd</c><c>   1</c></rc>
    <rc><c>Pd</c><c>   1</c></rc>
    <rc><c>C </c><c>   2</c></rc>
    <rc><c>O </c><c>   3</c></rc>
   </set>
  </array>
  <array name="atomtypes" >
   <dimension dim="1">type</dimension>
   <field type="int">atomspertype</field>
   <field type="string">element</field>
   <field>mass</field>
   <field>valence</field>
   <field type="string">pseudopotential</field>
   <set>
    <rc><c>  55</c><c>Pd</c><c>    106.42000000</c><c>     10.00000000</c><c>  PAW_PBE Pd 04Jan2005                  </c></rc>
    <rc><c>   1</c><c>C </c><c>     12.01100000</c><c>      4.00000000</c><c>  PAW_PBE C 08Apr2002                   </c></rc>
    <rc><c>   1</c><c>O </c><c>     16.00000000</c><c>      6.00000000</c><c>  PAW_PBE O 08Apr2002                   </c></rc>
   </set>
  </array>
 </atominfo>
 <structure name="initialpos" >
  <crystal>
   <varray name="basis" >
    <v>      30.00000000       0.00000000       0.00000000 </v>
    <v>       0.00000000      30.00000000       0.00000000 </v>
    <v>       0.00000000       0.00000000      30.00000000 </v>
   </varray>
   <i name="volume">  27000.00000000 </i>
   <varray name="rec_basis" >
    <v>       0.03333333       0.00000000       0.00000000 </v>
    <v>       0.00000000       0.03333333       0.00000000 </v>
    <v>       0.00000000       0.00000000       0.03333333 </v>
   </varray>
  </crystal>
  <varray name="positions" >
   <v>       0.44576020       0.32826710       0.41691983 </v>
   <v>       0.67173288       0.55423978       0.41691983 </v>
   <v>       0.55423980       0.32826710       0.41691983 </v>
   <v>       0.32826712       0.55423978       0.41691983 </v>
   <v>       0.50000000       0.38250690       0.34021317 </v>
   <v>       0.50000000       0.38250690       0.65978680 </v>
   <v>       0.50000000       0.27609440       0.50000000 </v>
   <v>       0.27609443       0.49999998       0.50000000 </v>
   <v>       0.72390557       0.49999998       0.50000000 </v>
   <v>       0.50000000       0.72390555       0.50000000 </v>
   <v>       0.61195280       0.38804720       0.34167483 </v>
   <v>       0.61195280       0.38804720       0.65832513 </v>
   <v>       0.38804722       0.61195278       0.34167483 </v>
   <v>       0.38804722       0.61195278       0.65832513 </v>
   <v>       0.38804720       0.38804720       0.34167483 </v>
   <v>       0.38804720       0.38804720       0.65832513 </v>
   <v>       0.61195278       0.61195278       0.34167483 </v>
   <v>       0.61195278       0.61195278       0.65832513 </v>
   <v>       0.44576020       0.32826710       0.58308023 </v>
   <v>       0.67173288       0.55423978       0.58308023 </v>
   <v>       0.55791699       0.44208301       0.41809300 </v>
   <v>       0.32826705       0.44576024       0.41691983 </v>
   <v>       0.55423973       0.67173293       0.41691983 </v>
   <v>       0.55423980       0.32826710       0.58308023 </v>
   <v>       0.32826712       0.55423978       0.58308023 </v>
   <v>       0.67173295       0.44576024       0.41691983 </v>
   <v>       0.44576027       0.67173293       0.41691983 </v>
   <v>       0.44208301       0.44208301       0.41809300 </v>
   <v>       0.50000000       0.38416601       0.50000000 </v>
   <v>       0.61749315       0.50000005       0.34021317 </v>
   <v>       0.61749315       0.50000005       0.65978680 </v>
   <v>       0.38250685       0.50000005       0.34021317 </v>
   <v>       0.38250685       0.50000005       0.65978680 </v>
   <v>       0.38317830       0.38317830       0.50000000 </v>
   <v>       0.61682172       0.61682172       0.50000000 </v>
   <v>       0.61682170       0.38317830       0.50000000 </v>
   <v>       0.38317828       0.61682172       0.50000000 </v>
   <v>       0.50000000       0.50000000       0.33478917 </v>
   <v>       0.50000000       0.50000000       0.66521087 </v>
   <v>       0.32826705       0.44576024       0.58308023 </v>
   <v>       0.55423973       0.67173293       0.58308023 </v>
   <v>       0.55791699       0.44208301       0.58190703 </v>
   <v>       0.44208298       0.55791702       0.41809300 </v>
   <v>       0.44208301       0.44208301       0.58190703 </v>
   <v>       0.67173295       0.44576024       0.58308023 </v>
   <v>       0.44576027       0.67173293       0.58308023 </v>
   <v>       0.55791702       0.55791702       0.41809300 </v>
   <v>       0.38416599       0.50000002       0.50000000 </v>
   <v>       0.61583401       0.50000002       0.50000000 </v>
   <v>       0.50000000       0.61749319       0.34021317 </v>
   <v>       0.50000000       0.61749319       0.65978680 </v>
   <v>       0.50000000       0.50000000       0.50000000 </v>
   <v>       0.44208298       0.55791702       0.58190703 </v>
   <v>       0.55791702       0.55791702       0.58190703 </v>
   <v>       0.50000000       0.61583404       0.50000000 </v>
   <v>       0.26979247       0.46353870       0.54067847 </v>
   <v>       0.23320840       0.45774437       0.54714300 </v>
  </varray>
  <varray name="selective"  type="logical" >
   <v type="logical" >  F  F  F </v>
   <v type="logical" >  F  F  F </v>
   <v type="logical" >  F  F  F </v>
   <v type="logical" >  F  F  F </v>
   <v type="logical" >  F  F  F </v>
   <v type="logical" >  F  F  F </v>
   <v type="logical" >  F  F  F </v>
   <v type="logical" >  F  F  F </v>
   <v type="logical" >  F  F  F </v>
   <v type="logical" >  F  F  F </v>
   <v type="logical" >  F  F  F </v>
   <v type="logical" >  F  F  F </v>
   <v type="logical" >  F  F  F </v>
   <v type="logical" >  F  F  F </v>
   <v type="logical" >  F  F  F </v>
   <v type="logical" >  F  F  F </v>
   <v type="logical" >  F  F  F </v>
   <v type="logical" >  F  F  F </v>
   <v type="logical" >  F  F  F </v>
   <v type="logical" >  F  F  F </v>
   <v type="logical" >  F  F  F </v>
   <v type="logical" >  F  F  F </v>
   <v type="logical" >  F  F  F </v>
   <v type="logical" >  F  F  F </v>
   <v type="logical" >  F  F  F </v>
   <v type="logical" >  F  F  F </v>
   <v type="logical" >  F  F  F </v>
   <v type="logical" >  F  F  F </v>
   <v type="logical" >  F  F  F </v>
   <v type="logical" >  F  F  F </v>
   <v type="logical" >  F  F  F </v>
   <v type="logical" >  F  F  F </v>
   <v type="logical" >  F  F  F </v>
   <v type="logical" >  F  F  F </v>
   <v type="logical" >  F  F  F </v>
   <v type="logical" >  F  F  F </v>
   <v type="logical" >  F  F  F </v>
   <v type="logical" >  F  F  F </v>
   <v type="logical" >  F  F  F </v>
   <v type="logical" >  F  F  F </v>
   <v type="logical" >  F  F  F </v>
   <v type="logical" >  F  F  F </v>
   <v type="logical" >  F  F  F </v>
   <v type="logical" >  F  F  F </v>
   <v type="logical" >  F  F  F </v>
   <v type="logical" >  F  F  F </v>
   <v type="logical" >  F  F  F </v>
   <v type="logical" >  F  F  F </v>
   <v type="logical" >  F  F  F </v>
   <v type="logical" >  F  F  F </v>
   <v type="logical" >  F  F  F </v>
   <v type="logical" >  F  F  F </v>
   <v type="logical" >  F  F  F </v>
   <v type="logical" >  F  F  F </v>
   <v type="logical" >  F  F  F </v>
   <v type="logical" >  F  F  F </v>
   <v type="logical" >  F  F  F </v>
  </varray>
  <nose>
   <v>      -3.00000000       0.00000000       0.00010000       0.00010000 </v>
  </nose>
 </structure>
 <calculation>
  <scstep>
   <time name="dav">  321.94  321.97</time>
   <time name="total">  334.04  334.07</time>
   <energy>
    <i name="alphaZ">     75.25431677 </i>
    <i name="ewald"> 138792.94406017 </i>
    <i name="hartreedc">-182137.86909190 </i>
    <i name="XCdc">  -1701.65854457 </i>
    <i name="pawpsdc">  44873.02882129 </i>
    <i name="pawaedc"> -41398.84523641 </i>
    <i name="eentropy">      0.01539035 </i>
    <i name="bandstr">    814.52939184 </i>
    <i name="atom">  45086.50549395 </i>
    <i name="e_fr_energy">   4403.90460149 </i>
    <i name="e_wo_entrp">   4403.88921114 </i>
    <i name="e_0_energy">   4403.90075390 </i>
   </energy>
  </scstep>
  <scstep>
   <time name="dav">  516.68  516.68</time>
   <time name="total">  516.68  516.68</time>
   <energy>
    <i name="e_fr_energy">   2015.94296703 </i>
    <i name="e_wo_entrp">   2015.95610136 </i>
    <i name="e_0_energy">   2015.94625061 </i>
   </energy>
  </scstep>
  <scstep>
   <time name="dav">  435.55  435.56</time>
   <time name="total">  435.56  435.56</time>
   <energy>
    <i name="e_fr_energy">    233.03263180 </i>
    <i name="e_wo_entrp">    233.02828816 </i>
    <i name="e_0_energy">    233.03154589 </i>
   </energy>
  </scstep>
  <scstep>
   <time name="dav">  381.84  381.84</time>
   <time name="total">  381.84  381.84</time>
   <energy>
    <i name="e_fr_energy">   -134.85669637 </i>
    <i name="e_wo_entrp">   -134.84952077 </i>
    <i name="e_0_energy">   -134.85490247 </i>
   </energy>
  </scstep>
  <scstep>
   <time name="dav">  456.64  456.64</time>
   <time name="total">  480.02  480.03</time>
   <energy>
    <i name="e_fr_energy">   -180.32381328 </i>
    <i name="e_wo_entrp">   -180.84848609 </i>
    <i name="e_0_energy">   -180.45498148 </i>
   </energy>
  </scstep>
  <scstep>
   <time name="diag">   61.23   61.23</time>
   <time name="diis">  169.09  169.09</time>
   <time name="orth">   12.38   12.38</time>
   <time name="total">  277.24  277.24</time>
   <energy>
    <i name="e_fr_energy">   -178.88399072 </i>
    <i name="e_wo_entrp">   -178.63682988 </i>
    <i name="e_0_energy">   -178.82220051 </i>
   </energy>
  </scstep>
  <scstep>
   <time name="diag">   61.26   61.25</time>
   <time name="diis">  190.83  190.83</time>
   <time name="orth">   12.33   12.33</time>
   <time name="total">  298.91  298.91</time>
   <energy>
    <i name="e_fr_energy">   -183.87775023 </i>
    <i name="e_wo_entrp">   -183.72747690 </i>
    <i name="e_0_energy">   -183.84018190 </i>
   </energy>
  </scstep>
  <scstep>
   <time name="diag">   61.67   61.67</time>
   <time name="diis">  175.28  175.28</time>
   <time name="orth">   12.14   12.14</time>
   <time name="total">  283.79  283.80</time>
   <energy>
    <i name="e_fr_energy">   -188.95160976 </i>
    <i name="e_wo_entrp">   -188.81417293 </i>
    <i name="e_0_energy">   -188.91725055 </i>
   </energy>
  </scstep>
  <scstep>
   <time name="diag">   61.47   61.47</time>
   <time name="diis">  174.80  174.80</time>
   <time name="orth">   12.09   12.09</time>
   <time name="total">  282.85  282.85</time>
   <energy>
    <i name="e_fr_energy">   -185.31702607 </i>
    <i name="e_wo_entrp">   -185.12092424 </i>
    <i name="e_0_energy">   -185.26800061 </i>
   </energy>
  </scstep>
  <scstep>
   <time name="diag">   61.28   61.28</time>
   <time name="diis">  168.02  168.02</time>
   <time name="orth">   12.12   12.12</time>
   <time name="total">  276.12  276.12</time>
   <energy>
    <i name="e_fr_energy">   -181.70492218 </i>
    <i name="e_wo_entrp">   -181.66645420 </i>
    <i name="e_0_energy">   -181.69530518 </i>
   </energy>
  </scstep>
  <scstep>
   <time name="diag">   61.41   61.41</time>
   <time name="diis">  170.80  170.80</time>
   <time name="orth">   12.25   12.25</time>
   <time name="total">  279.70  279.70</time>
   <energy>
    <i name="e_fr_energy">   -179.74636026 </i>
    <i name="e_wo_entrp">   -179.70195249 </i>
    <i name="e_0_energy">   -179.73525832 </i>
   </energy>
  </scstep>
  <scstep>
   <time name="diag">   62.33   62.33</time>
   <time name="diis">  169.60  169.60</time>
   <time name="orth">   12.44   12.44</time>
   <time name="total">  280.24  280.24</time>
   <energy>
    <i name="e_fr_energy">   -178.18674425 </i>
    <i name="e_wo_entrp">   -178.09408755 </i>
    <i name="e_0_energy">   -178.16358008 </i>
   </energy>
  </scstep>
  <scstep>
   <time name="diag">   62.45   62.45</time>
   <time name="diis">  168.78  168.78</time>
   <time name="orth">   12.50   12.50</time>
   <time name="total">  279.39  279.39</time>
   <energy>
    <i name="e_fr_energy">   -176.52934592 </i>
    <i name="e_wo_entrp">   -176.45847444 </i>
    <i name="e_0_energy">   -176.51162805 </i>
   </energy>
  </scstep>
  <scstep>
   <time name="diag">   61.73   61.73</time>
   <time name="diis">  162.52  162.52</time>
   <time name="orth">   12.07   12.07</time>
   <time name="total">  271.69  271.69</time>
   <energy>
    <i name="e_fr_energy">   -177.92368221 </i>
    <i name="e_wo_entrp">   -178.27765361 </i>
    <i name="e_0_energy">   -178.01217506 </i>
   </energy>
  </scstep>
  <scstep>
   <time name="diag">   61.21   61.21</time>
   <time name="diis">  163.96  163.96</time>
   <time name="orth">   12.08   12.08</time>
   <time name="total">  271.86  271.86</time>
   <energy>
    <i name="e_fr_energy">   -176.57233734 </i>
    <i name="e_wo_entrp">   -176.73443475 </i>
    <i name="e_0_energy">   -176.61286169 </i>
   </energy>
  </scstep>
  <scstep>
   <time name="diag">   61.10   61.10</time>
   <time name="diis">  164.65  164.65</time>
   <time name="orth">   12.11   12.11</time>
   <time name="total">  272.72  272.72</time>
   <energy>
    <i name="e_fr_energy">   -176.52777168 </i>
    <i name="e_wo_entrp">   -176.56819294 </i>
    <i name="e_0_energy">   -176.53787700 </i>
   </energy>
  </scstep>
  <scstep>
   <time name="diag">   61.16   61.16</time>
   <time name="diis">  164.10  164.10</time>
   <time name="orth">   12.04   12.04</time>
   <time name="total">  271.91  271.91</time>
   <energy>
    <i name="e_fr_energy">   -176.06004005 </i>
    <i name="e_wo_entrp">   -175.97068056 </i>
    <i name="e_0_energy">   -176.03770018 </i>
   </energy>
  </scstep>
  <scstep>
   <time name="diag">   61.21   61.21</time>
   <time name="diis">  162.30  162.30</time>
   <time name="orth">   12.19   12.19</time>
   <time name="total">  270.44  270.44</time>
   <energy>
    <i name="e_fr_energy">   -175.51180186 </i>
    <i name="e_wo_entrp">   -175.49670027 </i>
    <i name="e_0_energy">   -175.50802646 </i>
   </energy>
  </scstep>
  <scstep>
   <time name="diag">   61.21   61.21</time>
   <time name="diis">  163.77  163.77</time>
   <time name="orth">   12.23   12.23</time>
   <time name="total">  271.93  271.93</time>
   <energy>
    <i name="e_fr_energy">   -175.53163627 </i>
    <i name="e_wo_entrp">   -175.55259030 </i>
    <i name="e_0_energy">   -175.53687478 </i>
   </energy>
  </scstep>
  <scstep>
   <time name="diag">   61.20   61.20</time>
   <time name="diis">  161.82  161.82</time>
   <time name="orth">   12.15   12.15</time>
   <time name="total">  270.06  270.07</time>
   <energy>
    <i name="e_fr_energy">   -175.32858829 </i>
    <i name="e_wo_entrp">   -175.33135619 </i>
    <i name="e_0_energy">   -175.32928026 </i>
   </energy>
  </scstep>
  <scstep>
   <time name="diag">   61.38   61.38</time>
   <time name="diis">  161.37  161.37</time>
   <time name="orth">   12.09   12.09</time>
   <time name="total">  269.72  269.72</time>
   <energy>
    <i name="e_fr_energy">   -175.21102825 </i>
    <i name="e_wo_entrp">   -175.23183007 </i>
    <i name="e_0_energy">   -175.21622870 </i>
   </energy>
  </scstep>
  <scstep>
   <time name="diag">   61.23   61.23</time>
   <time name="diis">  160.67  160.67</time>
   <time name="orth">   12.12   12.12</time>
   <time name="total">  268.86  268.87</time>
   <energy>
    <i name="e_fr_energy">   -175.07372763 </i>
    <i name="e_wo_entrp">   -175.05813224 </i>
    <i name="e_0_energy">   -175.06982878 </i>
   </energy>
  </scstep>
  <scstep>
   <time name="diag">   61.04   61.04</time>
   <time name="diis">  160.13  160.14</time>
   <time name="orth">   12.17   12.17</time>
   <time name="total">  268.23  268.23</time>
   <energy>
    <i name="e_fr_energy">   -174.84123531 </i>
    <i name="e_wo_entrp">   -174.83781840 </i>
    <i name="e_0_energy">   -174.84038109 </i>
   </energy>
  </scstep>
  <scstep>
   <time name="diag">   61.09   61.09</time>
   <time name="diis">  164.33  164.33</time>
   <time name="orth">   12.47   12.47</time>
   <time name="total">  272.97  272.97</time>
   <energy>
    <i name="e_fr_energy">   -174.56781540 </i>
    <i name="e_wo_entrp">   -174.55518179 </i>
    <i name="e_0_energy">   -174.56465700 </i>
   </energy>
  </scstep>
  <scstep>
   <time name="diag">   61.98   61.98</time>
   <time name="diis">  163.32  163.32</time>
   <time name="orth">   12.47   12.47</time>
   <time name="total">  273.26  273.27</time>
   <energy>
    <i name="e_fr_energy">   -174.45544609 </i>
    <i name="e_wo_entrp">   -174.42955988 </i>
    <i name="e_0_energy">   -174.44897453 </i>
   </energy>
  </scstep>
  <scstep>
   <time name="diag">   62.11   62.11</time>
   <time name="diis">  164.92  164.92</time>
   <time name="orth">   12.52   12.52</time>
   <time name="total">  275.25  275.25</time>
   <energy>
    <i name="e_fr_energy">   -174.44286991 </i>
    <i name="e_wo_entrp">   -174.42442023 </i>
    <i name="e_0_energy">   -174.43825749 </i>
   </energy>
  </scstep>
  <scstep>
   <time name="diag">   61.39   61.39</time>
   <time name="diis">  165.02  165.02</time>
   <time name="orth">   12.21   12.21</time>
   <time name="total">  273.77  273.77</time>
   <energy>
    <i name="e_fr_energy">   -174.34362148 </i>
    <i name="e_wo_entrp">   -174.30621628 </i>
    <i name="e_0_energy">   -174.33427018 </i>
   </energy>
  </scstep>
  <scstep>
   <time name="diag">   61.49   61.49</time>
   <time name="diis">  162.78  162.78</time>
   <time name="orth">   12.37   12.37</time>
   <time name="total">  272.66  272.67</time>
   <energy>
    <i name="e_fr_energy">   -174.28721238 </i>
    <i name="e_wo_entrp">   -174.26470571 </i>
    <i name="e_0_energy">   -174.28158571 </i>
   </energy>
  </scstep>
  <scstep>
   <time name="diag">   61.84   61.84</time>
   <time name="diis">  161.02  161.02</time>
   <time name="orth">   12.19   12.19</time>
   <time name="total">  271.20  271.20</time>
   <energy>
    <i name="e_fr_energy">   -174.26126962 </i>
    <i name="e_wo_entrp">   -174.23912426 </i>
    <i name="e_0_energy">   -174.25573328 </i>
   </energy>
  </scstep>
  <scstep>
   <time name="diag">   61.59   61.59</time>
   <time name="diis">  163.05  163.05</time>
   <time name="orth">   12.36   12.36</time>
   <time name="total">  273.09  273.09</time>
   <energy>
    <i name="e_fr_energy">   -174.25329353 </i>
    <i name="e_wo_entrp">   -174.22728567 </i>
    <i name="e_0_energy">   -174.24679156 </i>
   </energy>
  </scstep>
  <scstep>
   <time name="diag">   62.27   62.27</time>
   <time name="diis">  160.87  160.87</time>
   <time name="orth">   12.20   12.20</time>
   <time name="total">  271.54  271.54</time>
   <energy>
    <i name="e_fr_energy">   -174.22866220 </i>
    <i name="e_wo_entrp">   -174.19871646 </i>
    <i name="e_0_energy">   -174.22117576 </i>
   </energy>
  </scstep>
  <scstep>
   <time name="diag">   61.71   61.71</time>
   <time name="diis">  160.56  160.56</time>
   <time name="orth">   12.27   12.27</time>
   <time name="total">  270.64  270.64</time>
   <energy>
    <i name="e_fr_energy">   -174.22772228 </i>
    <i name="e_wo_entrp">   -174.19196713 </i>
    <i name="e_0_energy">   -174.21878349 </i>
   </energy>
  </scstep>
  <scstep>
   <time name="diag">   62.18   62.18</time>
   <time name="diis">  162.75  162.75</time>
   <time name="orth">   12.55   12.55</time>
   <time name="total">  273.60  273.60</time>
   <energy>
    <i name="e_fr_energy">   -174.20540362 </i>
    <i name="e_wo_entrp">   -174.16940997 </i>
    <i name="e_0_energy">   -174.19640521 </i>
   </energy>
  </scstep>
  <scstep>
   <time name="diag">   61.67   61.67</time>
   <time name="diis">  160.89  160.89</time>
   <time name="orth">   12.33   12.33</time>
   <time name="total">  270.58  270.58</time>
   <energy>
    <i name="e_fr_energy">   -174.19393869 </i>
    <i name="e_wo_entrp">   -174.15941270 </i>
    <i name="e_0_energy">   -174.18530719 </i>
   </energy>
  </scstep>
  <scstep>
   <time name="diag">   61.44   61.44</time>
   <time name="diis">  160.14  160.14</time>
   <time name="orth">   12.35   12.35</time>
   <time name="total">  269.71  269.71</time>
   <energy>
    <i name="e_fr_energy">   -174.19145341 </i>
    <i name="e_wo_entrp">   -174.15799213 </i>
    <i name="e_0_energy">   -174.18308809 </i>
   </energy>
  </scstep>
  <scstep>
   <time name="diag">   61.52   61.52</time>
   <time name="diis">  161.89  161.89</time>
   <time name="orth">   12.57   12.57</time>
   <time name="total">  272.54  272.54</time>
   <energy>
    <i name="e_fr_energy">   -174.18831059 </i>
    <i name="e_wo_entrp">   -174.14834306 </i>
    <i name="e_0_energy">   -174.17831870 </i>
   </energy>
  </scstep>
  <scstep>
   <time name="diag">   62.57   62.57</time>
   <time name="diis">  163.44  163.44</time>
   <time name="orth">   12.31   12.31</time>
   <time name="total">  274.68  274.69</time>
   <energy>
    <i name="e_fr_energy">   -174.18600224 </i>
    <i name="e_wo_entrp">   -174.14389444 </i>
    <i name="e_0_energy">   -174.17547529 </i>
   </energy>
  </scstep>
  <scstep>
   <time name="diag">   61.73   61.74</time>
   <time name="diis">  159.52  159.52</time>
   <time name="orth">   12.39   12.39</time>
   <time name="total">  269.79  269.79</time>
   <energy>
    <i name="e_fr_energy">   -174.18706088 </i>
    <i name="e_wo_entrp">   -174.14272071 </i>
    <i name="e_0_energy">   -174.17597584 </i>
   </energy>
  </scstep>
  <scstep>
   <time name="diag">   61.49   61.49</time>
   <time name="diis">  158.97  158.97</time>
   <time name="orth">   12.31   12.31</time>
   <time name="total">  269.16  269.16</time>
   <energy>
    <i name="e_fr_energy">   -174.18584071 </i>
    <i name="e_wo_entrp">   -174.14179941 </i>
    <i name="e_0_energy">   -174.17483039 </i>
   </energy>
  </scstep>
  <scstep>
   <time name="diag">   61.63   61.63</time>
   <time name="diis">  158.29  158.29</time>
   <time name="orth">   12.32   12.32</time>
   <time name="total">  268.69  268.69</time>
   <energy>
    <i name="e_fr_energy">   -174.18703487 </i>
    <i name="e_wo_entrp">   -174.14530286 </i>
    <i name="e_0_energy">   -174.17660187 </i>
   </energy>
  </scstep>
  <scstep>
   <time name="diag">   61.47   61.47</time>
   <time name="diis">  158.75  158.76</time>
   <time name="orth">   12.45   12.45</time>
   <time name="total">  269.66  269.66</time>
   <energy>
    <i name="e_fr_energy">   -174.18778739 </i>
    <i name="e_wo_entrp">   -174.14645217 </i>
    <i name="e_0_energy">   -174.17745359 </i>
   </energy>
  </scstep>
  <scstep>
   <time name="diag">   62.63   62.63</time>
   <time name="diis">  150.12  150.12</time>
   <time name="orth">   12.60   12.60</time>
   <time name="total">  262.71  262.71</time>
   <energy>
    <i name="e_fr_energy">   -174.18882687 </i>
    <i name="e_wo_entrp">   -174.14722988 </i>
    <i name="e_0_energy">   -174.17842762 </i>
   </energy>
  </scstep>
  <scstep>
   <time name="diag">   62.28   62.28</time>
   <time name="diis">  155.09  155.08</time>
   <time name="orth">   12.42   12.42</time>
   <time name="total">  267.62  267.62</time>
   <energy>
    <i name="e_fr_energy">   -174.19157019 </i>
    <i name="e_wo_entrp">   -174.14622659 </i>
    <i name="e_0_energy">   -174.18023429 </i>
   </energy>
  </scstep>
  <scstep>
   <time name="diag">   61.81   61.81</time>
   <time name="diis">  135.84  135.84</time>
   <time name="orth">   12.37   12.37</time>
   <time name="total">  247.19  247.19</time>
   <energy>
    <i name="e_fr_energy">   -174.19393814 </i>
    <i name="e_wo_entrp">   -174.15070860 </i>
    <i name="e_0_energy">   -174.18313075 </i>
   </energy>
  </scstep>
  <scstep>
   <time name="diag">   62.16   62.16</time>
   <time name="diis">  133.02  133.02</time>
   <time name="orth">   12.37   12.37</time>
   <time name="total">  244.92  244.92</time>
   <energy>
    <i name="e_fr_energy">   -174.19675993 </i>
    <i name="e_wo_entrp">   -174.15469697 </i>
    <i name="e_0_energy">   -174.18624419 </i>
   </energy>
  </scstep>
  <scstep>
   <time name="diag">   61.69   61.69</time>
   <time name="diis">  108.35  108.35</time>
   <time name="orth">   12.36   12.36</time>
   <time name="total">  220.09  220.09</time>
   <energy>
    <i name="e_fr_energy">   -174.19851728 </i>
    <i name="e_wo_entrp">   -174.15652179 </i>
    <i name="e_0_energy">   -174.18801841 </i>
   </energy>
  </scstep>
  <scstep>
   <time name="diag">   61.54   61.54</time>
   <time name="diis">  131.76  131.76</time>
   <time name="orth">   12.43   12.43</time>
   <time name="total">  243.33  243.33</time>
   <energy>
    <i name="e_fr_energy">   -174.20191781 </i>
    <i name="e_wo_entrp">   -174.15986228 </i>
    <i name="e_0_energy">   -174.19140393 </i>
   </energy>
  </scstep>
  <scstep>
   <time name="diag">   61.76   61.76</time>
   <time name="diis">  111.10  111.10</time>
   <time name="orth">   12.43   12.43</time>
   <time name="total">  222.95  222.95</time>
   <energy>
    <i name="e_fr_energy">   -174.20367677 </i>
    <i name="e_wo_entrp">   -174.16075154 </i>
    <i name="e_0_energy">   -174.19294546 </i>
   </energy>
  </scstep>
  <scstep>
   <time name="diag">   62.44   62.44</time>
   <time name="diis">  105.89  105.90</time>
   <time name="orth">   12.52   12.52</time>
   <time name="total">  219.43  219.43</time>
   <energy>
    <i name="e_fr_energy">   -174.20517593 </i>
    <i name="e_wo_entrp">   -174.16330330 </i>
    <i name="e_0_energy">   -174.19470777 </i>
   </energy>
  </scstep>
  <scstep>
   <time name="diag">   62.52   62.52</time>
   <time name="diis">  114.81  114.82</time>
   <time name="orth">   12.47   12.47</time>
   <time name="total">  228.59  228.59</time>
   <energy>
    <i name="e_fr_energy">   -174.20715290 </i>
    <i name="e_wo_entrp">   -174.16449655 </i>
    <i name="e_0_energy">   -174.19648882 </i>
   </energy>
  </scstep>
  <scstep>
   <time name="diag">   63.45   63.45</time>
   <time name="diis">  105.51  105.51</time>
   <time name="orth">   12.20   12.20</time>
   <time name="total">  218.88  218.88</time>
   <energy>
    <i name="e_fr_energy">   -174.20770302 </i>
    <i name="e_wo_entrp">   -174.16580798 </i>
    <i name="e_0_energy">   -174.19722926 </i>
   </energy>
  </scstep>
  <scstep>
   <time name="diag">   61.51   61.51</time>
   <time name="diis">  101.56  101.56</time>
   <time name="orth">   12.43   12.43</time>
   <time name="total">  212.98  212.98</time>
   <energy>
    <i name="e_fr_energy">   -174.20926982 </i>
    <i name="e_wo_entrp">   -174.16726695 </i>
    <i name="e_0_energy">   -174.19876910 </i>
   </energy>
  </scstep>
  <scstep>
   <time name="diag">   61.62   61.62</time>
   <time name="diis">  101.99  101.99</time>
   <time name="orth">   12.23   12.23</time>
   <time name="total">  213.57  213.57</time>
   <energy>
    <i name="e_fr_energy">   -174.20971000 </i>
    <i name="e_wo_entrp">   -174.16751264 </i>
    <i name="e_0_energy">   -174.19916066 </i>
   </energy>
  </scstep>
  <scstep>
   <time name="diag">   61.41   61.41</time>
   <time name="diis">  102.50  102.50</time>
   <time name="orth">   12.30   12.30</time>
   <time name="total">  214.29  214.29</time>
   <energy>
    <i name="e_fr_energy">   -174.21051837 </i>
    <i name="e_wo_entrp">   -174.16819986 </i>
    <i name="e_0_energy">   -174.19993875 </i>
   </energy>
  </scstep>
  <scstep>
   <time name="diag">   62.14   62.14</time>
   <time name="diis">  100.27  100.27</time>
   <time name="orth">   12.31   12.31</time>
   <time name="total">  212.50  212.51</time>
   <energy>
    <i name="e_fr_energy">   -174.21097895 </i>
    <i name="e_wo_entrp">   -174.16868124 </i>
    <i name="e_0_energy">   -174.20040452 </i>
   </energy>
  </scstep>
  <scstep>
   <time name="diag">   61.91   61.91</time>
   <time name="diis">   87.16   87.16</time>
   <time name="orth">   12.12   12.12</time>
   <time name="total">  198.92  198.93</time>
   <energy>
    <i name="e_fr_energy">   -174.21120134 </i>
    <i name="e_wo_entrp">   -174.16893478 </i>
    <i name="e_0_energy">   -174.20063470 </i>
   </energy>
  </scstep>
  <scstep>
   <time name="diag">   62.10   62.10</time>
   <time name="diis">   84.54   84.54</time>
   <time name="orth">   12.14   12.14</time>
   <time name="total">  196.77  196.78</time>
   <energy>
    <i name="e_fr_energy">   -174.21161499 </i>
    <i name="e_wo_entrp">   -174.16929432 </i>
    <i name="e_0_energy">   -174.20103482 </i>
   </energy>
  </scstep>
  <scstep>
   <time name="diag">   61.87   61.87</time>
   <time name="diis">   71.86   71.86</time>
   <time name="orth">   12.26   12.26</time>
   <time name="total">  184.14  184.14</time>
   <energy>
    <i name="e_fr_energy">   -174.21182049 </i>
    <i name="e_wo_entrp">   -174.16961153 </i>
    <i name="e_0_energy">   -174.20126825 </i>
   </energy>
  </scstep>
  <scstep>
   <time name="diag">   61.68   61.68</time>
   <time name="diis">   76.72   76.72</time>
   <time name="orth">   12.15   12.15</time>
   <time name="total">  188.58  188.58</time>
   <energy>
    <i name="e_fr_energy">   -174.21205575 </i>
    <i name="e_wo_entrp">   -174.16988399 </i>
    <i name="e_0_energy">   -174.20151281 </i>
   </energy>
  </scstep>
  <scstep>
   <time name="diag">   62.05   62.06</time>
   <time name="diis">   82.03   82.03</time>
   <time name="orth">   12.48   12.48</time>
   <time name="total">  194.46  194.46</time>
   <energy>
    <i name="e_fr_energy">   -174.21238913 </i>
    <i name="e_wo_entrp">   -174.17013852 </i>
    <i name="e_0_energy">   -174.20182648 </i>
   </energy>
  </scstep>
  <scstep>
   <time name="diag">   62.36   62.36</time>
   <time name="diis">   71.50   71.50</time>
   <time name="orth">   12.62   12.62</time>
   <time name="total">  185.41  185.41</time>
   <energy>
    <i name="e_fr_energy">   -174.21250201 </i>
    <i name="e_wo_entrp">   -174.17032771 </i>
    <i name="e_0_energy">   -174.20195844 </i>
   </energy>
  </scstep>
  <scstep>
   <time name="diag">   62.68   62.68</time>
   <time name="diis">   75.22   75.22</time>
   <time name="orth">   12.57   12.57</time>
   <time name="total">  189.74  189.75</time>
   <energy>
    <i name="e_fr_energy">   -174.21270617 </i>
    <i name="e_wo_entrp">   -174.17055172 </i>
    <i name="e_0_energy">   -174.20216756 </i>
   </energy>
  </scstep>
  <scstep>
   <time name="diag">   63.45   63.45</time>
   <time name="diis">   76.05   76.06</time>
   <time name="orth">   12.56   12.56</time>
   <time name="total">  191.15  191.17</time>
   <energy>
    <i name="e_fr_energy">   -174.21283229 </i>
    <i name="e_wo_entrp">   -174.17063214 </i>
    <i name="e_0_energy">   -174.20228226 </i>
   </energy>
  </scstep>
  <scstep>
   <time name="diag">   62.04   62.04</time>
   <time name="diis">   73.30   73.30</time>
   <time name="orth">   12.21   12.21</time>
   <time name="total">  159.55  159.56</time>
   <energy>
    <i name="alphaZ">     75.25431677 </i>
    <i name="ewald"> 138792.94406017 </i>
    <i name="hartreedc">-183136.75394537 </i>
    <i name="XCdc">  -1690.83940345 </i>
    <i name="pawpsdc">  46418.20027926 </i>
    <i name="pawaedc"> -42890.27963469 </i>
    <i name="eentropy">     -0.04220113 </i>
    <i name="bandstr">  -2829.20188238 </i>
    <i name="atom">  45086.50549395 </i>
    <i name="e_fr_energy">   -174.21291688 </i>
    <i name="e_wo_entrp">   -174.17071575 </i>
    <i name="e_0_energy">   -174.20236660 </i>
   </energy>
  </scstep>
  <structure>
   <crystal>
    <varray name="basis" >
     <v>      30.00000000       0.00000000       0.00000000 </v>
     <v>       0.00000000      30.00000000       0.00000000 </v>
     <v>       0.00000000       0.00000000      30.00000000 </v>
    </varray>
    <i name="volume">  27000.00000000 </i>
    <varray name="rec_basis" >
     <v>       0.03333333       0.00000000       0.00000000 </v>
     <v>       0.00000000       0.03333333       0.00000000 </v>
     <v>       0.00000000       0.00000000       0.03333333 </v>
    </varray>
   </crystal>
   <varray name="positions" >
    <v>       0.44576020       0.32826710       0.41691983 </v>
    <v>       0.67173288       0.55423978       0.41691983 </v>
    <v>       0.55423980       0.32826710       0.41691983 </v>
    <v>       0.32826712       0.55423978       0.41691983 </v>
    <v>       0.50000000       0.38250690       0.34021317 </v>
    <v>       0.50000000       0.38250690       0.65978680 </v>
    <v>       0.50000000       0.27609440       0.50000000 </v>
    <v>       0.27609443       0.49999998       0.50000000 </v>
    <v>       0.72390557       0.49999998       0.50000000 </v>
    <v>       0.50000000       0.72390555       0.50000000 </v>
    <v>       0.61195280       0.38804720       0.34167483 </v>
    <v>       0.61195280       0.38804720       0.65832513 </v>
    <v>       0.38804722       0.61195278       0.34167483 </v>
    <v>       0.38804722       0.61195278       0.65832513 </v>
    <v>       0.38804720       0.38804720       0.34167483 </v>
    <v>       0.38804720       0.38804720       0.65832513 </v>
    <v>       0.61195278       0.61195278       0.34167483 </v>
    <v>       0.61195278       0.61195278       0.65832513 </v>
    <v>       0.44576020       0.32826710       0.58308023 </v>
    <v>       0.67173288       0.55423978       0.58308023 </v>
    <v>       0.55791699       0.44208301       0.41809300 </v>
    <v>       0.32826705       0.44576024       0.41691983 </v>
    <v>       0.55423973       0.67173293       0.41691983 </v>
    <v>       0.55423980       0.32826710       0.58308023 </v>
    <v>       0.32826712       0.55423978       0.58308023 </v>
    <v>       0.67173295       0.44576024       0.41691983 </v>
    <v>       0.44576027       0.67173293       0.41691983 </v>
    <v>       0.44208301       0.44208301       0.41809300 </v>
    <v>       0.50000000       0.38416601       0.50000000 </v>
    <v>       0.61749315       0.50000005       0.34021317 </v>
    <v>       0.61749315       0.50000005       0.65978680 </v>
    <v>       0.38250685       0.50000005       0.34021317 </v>
    <v>       0.38250685       0.50000005       0.65978680 </v>
    <v>       0.38317830       0.38317830       0.50000000 </v>
    <v>       0.61682172       0.61682172       0.50000000 </v>
    <v>       0.61682170       0.38317830       0.50000000 </v>
    <v>       0.38317828       0.61682172       0.50000000 </v>
    <v>       0.50000000       0.50000000       0.33478917 </v>
    <v>       0.50000000       0.50000000       0.66521087 </v>
    <v>       0.32826705       0.44576024       0.58308023 </v>
    <v>       0.55423973       0.67173293       0.58308023 </v>
    <v>       0.55791699       0.44208301       0.58190703 </v>
    <v>       0.44208298       0.55791702       0.41809300 </v>
    <v>       0.44208301       0.44208301       0.58190703 </v>
    <v>       0.67173295       0.44576024       0.58308023 </v>
    <v>       0.44576027       0.67173293       0.58308023 </v>
    <v>       0.55791702       0.55791702       0.41809300 </v>
    <v>       0.38416599       0.50000002       0.50000000 </v>
    <v>       0.61583401       0.50000002       0.50000000 </v>
    <v>       0.50000000       0.61749319       0.34021317 </v>
    <v>       0.50000000       0.61749319       0.65978680 </v>
    <v>       0.50000000       0.50000000       0.50000000 </v>
    <v>       0.44208298       0.55791702       0.58190703 </v>
    <v>       0.55791702       0.55791702       0.58190703 </v>
    <v>       0.50000000       0.61583404       0.50000000 </v>
    <v>       0.26979247       0.46353870       0.54067847 </v>
    <v>       0.23320840       0.45774437       0.54714300 </v>
   </varray>
  </structure>
  <varray name="forces" >
   <v>       0.70808061       1.10277808       0.29149465 </v>
   <v>      -1.11356661      -0.69809372       0.28010779 </v>
   <v>      -0.70316053       1.10653979       0.29608095 </v>
   <v>       1.18149829      -0.66942265       0.15600152 </v>
   <v>       0.00567274       0.40839503       1.28151287 </v>
   <v>      -0.01373479       0.41886026      -1.27218738 </v>
   <v>       0.00042681       1.51766099      -0.00213874 </v>
   <v>       3.34342466       5.83148231      -6.65967963 </v>
   <v>      -1.51191635      -0.00437954       0.00491077 </v>
   <v>       0.00205309      -1.51863704      -0.00346282 </v>
   <v>      -0.75505305       0.75364219       1.07003105 </v>
   <v>      -0.75283393       0.75662573      -1.07445802 </v>
   <v>       0.76067719      -0.73446551       1.05614692 </v>
   <v>       0.72907764      -0.75813916      -1.09764274 </v>
   <v>       0.75617429       0.75628291       1.06520281 </v>
   <v>       0.77161036       0.76296359      -1.06976279 </v>
   <v>      -0.75802197      -0.75379298       1.07100952 </v>
   <v>      -0.75464910      -0.75561190      -1.07215271 </v>
   <v>       0.70872479       1.10909440      -0.29198086 </v>
   <v>      -1.11652881      -0.69364056      -0.28092070 </v>
   <v>       0.11290190      -0.11196113      -0.14300221 </v>
   <v>       1.17371569       0.70262254       0.15529186 </v>
   <v>      -0.70588654      -1.10386053       0.29211679 </v>
   <v>      -0.70380068       1.10522612      -0.29786029 </v>
   <v>       1.18968316      -0.61577865      -0.10980185 </v>
   <v>      -1.11332901       0.69537837       0.28632827 </v>
   <v>       0.71004563      -1.10681884       0.29291004 </v>
   <v>      -0.10881883      -0.10299642      -0.16458116 </v>
   <v>      -0.00494314      -0.23072122      -0.00006169 </v>
   <v>      -0.40941151       0.00062028       1.27623641 </v>
   <v>      -0.40089410      -0.00053152      -1.28179829 </v>
   <v>       0.38348532      -0.01625052       1.29665169 </v>
   <v>       0.49288231       0.01635077      -1.22981277 </v>
   <v>       0.85970926       0.78947829      -0.00767421 </v>
   <v>      -0.83068087      -0.82481111       0.00164619 </v>
   <v>      -0.82679591       0.82630181      -0.00148209 </v>
   <v>       0.84095974      -0.82012567      -0.01102694 </v>
   <v>       0.00533759      -0.00424634       1.18359215 </v>
   <v>      -0.02624751      -0.00227530      -1.18026839 </v>
   <v>       0.00370677       0.93596709      -1.09589112 </v>
   <v>      -0.70216244      -1.10743794      -0.29590020 </v>
   <v>       0.13960060      -0.11054219       0.15487142 </v>
   <v>      -0.11185664       0.10385393      -0.14657827 </v>
   <v>      -0.05717661      -0.10941934       0.16554329 </v>
   <v>      -1.11901462       0.69214432      -0.28307451 </v>
   <v>       0.70647423      -1.10648211      -0.29186772 </v>
   <v>       0.10864367       0.11102629      -0.14932298 </v>
   <v>      -0.09371679       0.04121948      -0.06119557 </v>
   <v>       0.23025498      -0.00009081      -0.00313898 </v>
   <v>       0.01361348      -0.40269755       1.28136182 </v>
   <v>       0.00360606      -0.41384059      -1.27756451 </v>
   <v>      -0.01271198       0.00081734       0.00352525 </v>
   <v>      -0.10622037       0.10228348       0.16328932 </v>
   <v>       0.11960454       0.11125790       0.14725062 </v>
   <v>      -0.00495551       0.23015436      -0.00149669 </v>
   <v>       7.51577009      -3.69295845       5.02724116 </v>
   <v>      -8.75932732      -2.51899836       2.55743174 </v>
  </varray>
  <varray name="stress" >
   <v>      -6.19207372       0.27121264      -0.33762831 </v>
   <v>       0.27121266      -6.32108534      -0.43217487 </v>
   <v>      -0.33762836      -0.43217487      -6.22504013 </v>
  </varray>
  <energy>
   <i name="e_fr_energy">   -174.21291688 </i>
   <i name="e_wo_entrp">   -174.20236660 </i>
   <i name="e_0_energy">     -0.04220113 </i>
  </energy>
  <time name="totalsc">17239.3917239.62</time>
  <eigenvalues>
   <array>
    <dimension dim="1">band</dimension>
    <dimension dim="2">kpoint</dimension>
    <dimension dim="3">spin</dimension>
    <field>eigene</field>
    <field>occ</field>
    <set>
     <set comment="spin 1">
      <set comment="kpoint 1">
       <r>  -28.2154    1.0000 </r>
       <r>  -13.7337    1.0000 </r>
       <r>  -11.6264    1.0000 </r>
       <r>  -11.1103    1.0000 </r>
       <r>  -10.6835    1.0000 </r>
       <r>   -6.9306    1.0000 </r>
       <r>   -6.6751    1.0000 </r>
       <r>   -6.6218    1.0000 </r>
       <r>   -6.1817    1.0000 </r>
       <r>   -6.1467    1.0000 </r>
       <r>   -6.1345    1.0000 </r>
       <r>   -6.0722    1.0000 </r>
       <r>   -5.9844    1.0000 </r>
       <r>   -5.9259    1.0000 </r>
       <r>   -5.8428    1.0000 </r>
       <r>   -5.8134    1.0000 </r>
       <r>   -5.7919    1.0000 </r>
       <r>   -5.7464    1.0000 </r>
       <r>   -5.6981    1.0000 </r>
       <r>   -5.6888    1.0000 </r>
       <r>   -5.6803    1.0000 </r>
       <r>   -5.6636    1.0000 </r>
       <r>   -5.6403    1.0000 </r>
       <r>   -5.6217    1.0000 </r>
       <r>   -5.6189    1.0000 </r>
       <r>   -5.6011    1.0000 </r>
       <r>   -5.5884    1.0000 </r>
       <r>   -5.5814    1.0000 </r>
       <r>   -5.5623    1.0000 </r>
       <r>   -5.5608    1.0000 </r>
       <r>   -5.5538    1.0000 </r>
       <r>   -5.5436    1.0000 </r>
       <r>   -5.5332    1.0000 </r>
       <r>   -5.5294    1.0000 </r>
       <r>   -5.5244    1.0000 </r>
       <r>   -5.5201    1.0000 </r>
       <r>   -5.5179    1.0000 </r>
       <r>   -5.5136    1.0000 </r>
       <r>   -5.5075    1.0000 </r>
       <r>   -5.4948    1.0000 </r>
       <r>   -5.4908    1.0000 </r>
       <r>   -5.4816    1.0000 </r>
       <r>   -5.4789    1.0000 </r>
       <r>   -5.4741    1.0000 </r>
       <r>   -5.4722    1.0000 </r>
       <r>   -5.4599    1.0000 </r>
       <r>   -5.4500    1.0000 </r>
       <r>   -5.4444    1.0000 </r>
       <r>   -5.4366    1.0000 </r>
       <r>   -5.4351    1.0000 </r>
       <r>   -5.4323    1.0000 </r>
       <r>   -5.4300    1.0000 </r>
       <r>   -5.4250    1.0000 </r>
       <r>   -5.4183    1.0000 </r>
       <r>   -5.4108    1.0000 </r>
       <r>   -5.4097    1.0000 </r>
       <r>   -5.3999    1.0000 </r>
       <r>   -5.3973    1.0000 </r>
       <r>   -5.3622    1.0000 </r>
       <r>   -5.3557    1.0000 </r>
       <r>   -5.3437    1.0000 </r>
       <r>   -5.3335    1.0000 </r>
       <r>   -5.3319    1.0000 </r>
       <r>   -5.3253    1.0000 </r>
       <r>   -5.3204    1.0000 </r>
       <r>   -5.3181    1.0000 </r>
       <r>   -5.3070    1.0000 </r>
       <r>   -5.3020    1.0000 </r>
       <r>   -5.2937    1.0000 </r>
       <r>   -5.2892    1.0000 </r>
       <r>   -5.2800    1.0000 </r>
       <r>   -5.2558    1.0000 </r>
       <r>   -5.2270    1.0000 </r>
       <r>   -5.2216    1.0000 </r>
       <r>   -5.2113    1.0000 </r>
       <r>   -5.2068    1.0000 </r>
       <r>   -5.1999    1.0000 </r>
       <r>   -5.1920    1.0000 </r>
       <r>   -5.1837    1.0000 </r>
       <r>   -5.1826    1.0000 </r>
       <r>   -5.1694    1.0000 </r>
       <r>   -5.1671    1.0000 </r>
       <r>   -5.1637    1.0000 </r>
       <r>   -5.1532    1.0000 </r>
       <r>   -5.1493    1.0000 </r>
       <r>   -5.1384    1.0000 </r>
       <r>   -5.1293    1.0000 </r>
       <r>   -5.1262    1.0000 </r>
       <r>   -5.1159    1.0000 </r>
       <r>   -5.1069    1.0000 </r>
       <r>   -5.0955    1.0000 </r>
       <r>   -5.0840    1.0000 </r>
       <r>   -5.0694    1.0000 </r>
       <r>   -5.0620    1.0000 </r>
       <r>   -5.0584    1.0000 </r>
       <r>   -5.0565    1.0000 </r>
       <r>   -5.0536    1.0000 </r>
       <r>   -5.0476    1.0000 </r>
       <r>   -5.0414    1.0000 </r>
       <r>   -5.0387    1.0000 </r>
       <r>   -5.0338    1.0000 </r>
       <r>   -5.0310    1.0000 </r>
       <r>   -5.0264    1.0000 </r>
       <r>   -5.0179    1.0000 </r>
       <r>   -5.0166    1.0000 </r>
       <r>   -5.0124    1.0000 </r>
       <r>   -5.0085    1.0000 </r>
       <r>   -4.9995    1.0000 </r>
       <r>   -4.9932    1.0000 </r>
       <r>   -4.9907    1.0000 </r>
       <r>   -4.9872    1.0000 </r>
       <r>   -4.9859    1.0000 </r>
       <r>   -4.9792    1.0000 </r>
       <r>   -4.9748    1.0000 </r>
       <r>   -4.9698    1.0000 </r>
       <r>   -4.9671    1.0000 </r>
       <r>   -4.9596    1.0000 </r>
       <r>   -4.9564    1.0000 </r>
       <r>   -4.9547    1.0000 </r>
       <r>   -4.9475    1.0000 </r>
       <r>   -4.9437    1.0000 </r>
       <r>   -4.9310    1.0000 </r>
       <r>   -4.9210    1.0000 </r>
       <r>   -4.9158    1.0000 </r>
       <r>   -4.9100    1.0000 </r>
       <r>   -4.9056    1.0000 </r>
       <r>   -4.9040    1.0000 </r>
       <r>   -4.9015    1.0000 </r>
       <r>   -4.8845    1.0000 </r>
       <r>   -4.8733    1.0000 </r>
       <r>   -4.8565    1.0000 </r>
       <r>   -4.8544    1.0000 </r>
       <r>   -4.8504    1.0000 </r>
       <r>   -4.8458    1.0000 </r>
       <r>   -4.8445    1.0000 </r>
       <r>   -4.8384    1.0000 </r>
       <r>   -4.8368    1.0000 </r>
       <r>   -4.8343    1.0000 </r>
       <r>   -4.8119    0.9999 </r>
       <r>   -4.8068    0.9999 </r>
       <r>   -4.8003    0.9999 </r>
       <r>   -4.7989    0.9999 </r>
       <r>   -4.7904    0.9999 </r>
       <r>   -4.7843    0.9999 </r>
       <r>   -4.7698    0.9998 </r>
       <r>   -4.7692    0.9998 </r>
       <r>   -4.7611    0.9997 </r>
       <r>   -4.7423    0.9996 </r>
       <r>   -4.7324    0.9995 </r>
       <r>   -4.7270    0.9995 </r>
       <r>   -4.7254    0.9994 </r>
       <r>   -4.7217    0.9994 </r>
       <r>   -4.7048    0.9991 </r>
       <r>   -4.6973    0.9990 </r>
       <r>   -4.6911    0.9989 </r>
       <r>   -4.6870    0.9988 </r>
       <r>   -4.6829    0.9987 </r>
       <r>   -4.6788    0.9986 </r>
       <r>   -4.6728    0.9985 </r>
       <r>   -4.6698    0.9984 </r>
       <r>   -4.6685    0.9984 </r>
       <r>   -4.6641    0.9982 </r>
       <r>   -4.6609    0.9981 </r>
       <r>   -4.6582    0.9981 </r>
       <r>   -4.6514    0.9978 </r>
       <r>   -4.6502    0.9978 </r>
       <r>   -4.6499    0.9978 </r>
       <r>   -4.6477    0.9977 </r>
       <r>   -4.6445    0.9976 </r>
       <r>   -4.6396    0.9975 </r>
       <r>   -4.6310    0.9971 </r>
       <r>   -4.6251    0.9969 </r>
       <r>   -4.6148    0.9965 </r>
       <r>   -4.6072    0.9963 </r>
       <r>   -4.6029    0.9961 </r>
       <r>   -4.6005    0.9960 </r>
       <r>   -4.5986    0.9959 </r>
       <r>   -4.5947    0.9958 </r>
       <r>   -4.5872    0.9956 </r>
       <r>   -4.5823    0.9954 </r>
       <r>   -4.5795    0.9954 </r>
       <r>   -4.5780    0.9953 </r>
       <r>   -4.5749    0.9953 </r>
       <r>   -4.5722    0.9952 </r>
       <r>   -4.5664    0.9951 </r>
       <r>   -4.5585    0.9951 </r>
       <r>   -4.5576    0.9951 </r>
       <r>   -4.5533    0.9951 </r>
       <r>   -4.5516    0.9951 </r>
       <r>   -4.5511    0.9951 </r>
       <r>   -4.5421    0.9953 </r>
       <r>   -4.5277    0.9959 </r>
       <r>   -4.5165    0.9969 </r>
       <r>   -4.5141    0.9971 </r>
       <r>   -4.5115    0.9974 </r>
       <r>   -4.5053    0.9982 </r>
       <r>   -4.5039    0.9984 </r>
       <r>   -4.4971    0.9994 </r>
       <r>   -4.4954    0.9997 </r>
       <r>   -4.4837    1.0021 </r>
       <r>   -4.4803    1.0029 </r>
       <r>   -4.4776    1.0036 </r>
       <r>   -4.4700    1.0056 </r>
       <r>   -4.4680    1.0062 </r>
       <r>   -4.4663    1.0067 </r>
       <r>   -4.4570    1.0098 </r>
       <r>   -4.4529    1.0113 </r>
       <r>   -4.4498    1.0124 </r>
       <r>   -4.4483    1.0130 </r>
       <r>   -4.4453    1.0142 </r>
       <r>   -4.4421    1.0154 </r>
       <r>   -4.4296    1.0209 </r>
       <r>   -4.4260    1.0225 </r>
       <r>   -4.4168    1.0268 </r>
       <r>   -4.4150    1.0277 </r>
       <r>   -4.4134    1.0285 </r>
       <r>   -4.4103    1.0299 </r>
       <r>   -4.4089    1.0306 </r>
       <r>   -4.3974    1.0361 </r>
       <r>   -4.3852    1.0416 </r>
       <r>   -4.3837    1.0423 </r>
       <r>   -4.3750    1.0456 </r>
       <r>   -4.3725    1.0465 </r>
       <r>   -4.3670    1.0482 </r>
       <r>   -4.3624    1.0495 </r>
       <r>   -4.3548    1.0509 </r>
       <r>   -4.3437    1.0516 </r>
       <r>   -4.3427    1.0516 </r>
       <r>   -4.3405    1.0514 </r>
       <r>   -4.3374    1.0510 </r>
       <r>   -4.3370    1.0510 </r>
       <r>   -4.3362    1.0508 </r>
       <r>   -4.3330    1.0502 </r>
       <r>   -4.3315    1.0498 </r>
       <r>   -4.3298    1.0493 </r>
       <r>   -4.3258    1.0479 </r>
       <r>   -4.3241    1.0471 </r>
       <r>   -4.3227    1.0465 </r>
       <r>   -4.3208    1.0455 </r>
       <r>   -4.3140    1.0413 </r>
       <r>   -4.3110    1.0391 </r>
       <r>   -4.3017    1.0304 </r>
       <r>   -4.2951    1.0227 </r>
       <r>   -4.2945    1.0219 </r>
       <r>   -4.2927    1.0195 </r>
       <r>   -4.2901    1.0158 </r>
       <r>   -4.2890    1.0141 </r>
       <r>   -4.2862    1.0099 </r>
       <r>   -4.2834    1.0052 </r>
       <r>   -4.2793    0.9979 </r>
       <r>   -4.2729    0.9855 </r>
       <r>   -4.2694    0.9779 </r>
       <r>   -4.2661    0.9704 </r>
       <r>   -4.2606    0.9569 </r>
       <r>   -4.2587    0.9520 </r>
       <r>   -4.2576    0.9490 </r>
       <r>   -4.2554    0.9431 </r>
       <r>   -4.2531    0.9367 </r>
       <r>   -4.2516    0.9323 </r>
       <r>   -4.2484    0.9230 </r>
       <r>   -4.2471    0.9189 </r>
       <r>   -4.2453    0.9133 </r>
       <r>   -4.2437    0.9082 </r>
       <r>   -4.2431    0.9063 </r>
       <r>   -4.2396    0.8948 </r>
       <r>   -4.2382    0.8899 </r>
       <r>   -4.2334    0.8733 </r>
       <r>   -4.2266    0.8480 </r>
       <r>   -4.2232    0.8347 </r>
       <r>   -4.2224    0.8316 </r>
       <r>   -4.2216    0.8283 </r>
       <r>   -4.2142    0.7978 </r>
       <r>   -4.2108    0.7832 </r>
       <r>   -4.2051    0.7579 </r>
       <r>   -4.1890    0.6818 </r>
       <r>   -4.1849    0.6611 </r>
       <r>   -4.1807    0.6400 </r>
       <r>   -4.1773    0.6230 </r>
       <r>   -4.1765    0.6189 </r>
       <r>   -4.1757    0.6146 </r>
       <r>   -4.1641    0.5541 </r>
       <r>   -4.1602    0.5334 </r>
       <r>   -4.1390    0.4219 </r>
       <r>   -4.1360    0.4060 </r>
       <r>   -4.1326    0.3888 </r>
       <r>   -4.1306    0.3782 </r>
       <r>   -4.1206    0.3278 </r>
       <r>   -4.1164    0.3075 </r>
       <r>   -4.0481    0.0458 </r>
       <r>   -3.9684   -0.0513 </r>
       <r>   -3.9043   -0.0333 </r>
       <r>   -3.8223   -0.0017 </r>
       <r>   -3.8180   -0.0008 </r>
       <r>   -3.6499    0.0020 </r>
       <r>   -3.5063    0.0001 </r>
       <r>   -3.5003    0.0001 </r>
       <r>   -3.3749    0.0000 </r>
       <r>   -3.0975    0.0000 </r>
       <r>   -3.0640    0.0000 </r>
       <r>   -3.0505    0.0000 </r>
       <r>   -3.0432    0.0000 </r>
       <r>   -3.0173    0.0000 </r>
       <r>   -2.9652    0.0000 </r>
       <r>   -2.9513    0.0000 </r>
       <r>   -2.7480    0.0000 </r>
       <r>   -2.5462    0.0000 </r>
       <r>   -2.5372    0.0000 </r>
       <r>   -2.3707    0.0000 </r>
       <r>   -2.3143    0.0000 </r>
       <r>   -2.1293    0.0000 </r>
       <r>   -2.1194    0.0000 </r>
       <r>   -2.0998    0.0000 </r>
       <r>   -2.0355    0.0000 </r>
       <r>   -1.9767    0.0000 </r>
       <r>   -1.9171    0.0000 </r>
       <r>   -1.8789    0.0000 </r>
       <r>   -1.7994    0.0000 </r>
       <r>   -1.7497    0.0000 </r>
       <r>   -1.6970    0.0000 </r>
       <r>   -1.6581    0.0000 </r>
       <r>   -1.5963    0.0000 </r>
       <r>   -1.5602    0.0000 </r>
       <r>   -1.3905    0.0000 </r>
       <r>   -1.2812    0.0000 </r>
       <r>   -1.2473    0.0000 </r>
       <r>   -1.1742    0.0000 </r>
       <r>   -1.0829    0.0000 </r>
       <r>   -1.0124    0.0000 </r>
       <r>   -0.9885    0.0000 </r>
       <r>   -0.9815    0.0000 </r>
       <r>   -0.9513    0.0000 </r>
       <r>   -0.9389    0.0000 </r>
       <r>   -0.9042    0.0000 </r>
       <r>   -0.8803    0.0000 </r>
       <r>   -0.8230    0.0000 </r>
       <r>   -0.7773    0.0000 </r>
      </set>
     </set>
    </set>
   </array>
  </eigenvalues>
  <separator name="orbital magnetization" >
   <v name="MAGDIPOLOUT">      0.00000000      0.00000000      0.00000000</v>
  </separator>
  <dos>
   <i name="efermi">     -4.15383411 </i>
   <total>
    <array>
     <dimension dim="1">gridpoints</dimension>
     <dimension dim="2">spin</dimension>
     <field>energy</field>
     <field>total</field>
     <field>integrated</field>
     <set>
      <set comment="spin 1">
       <r>   -30.2154     0.0000     0.0000 </r>
       <r>   -30.1106     0.0000     0.0000 </r>
       <r>   -30.0058     0.0000     0.0000 </r>
       <r>   -29.9010     0.0000     0.0000 </r>
       <r>   -29.7962     0.0000     0.0000 </r>
       <r>   -29.6914     0.0000     0.0000 </r>
       <r>   -29.5866     0.0000     0.0000 </r>
       <r>   -29.4818     0.0000     0.0000 </r>
       <r>   -29.3770     0.0000     0.0000 </r>
       <r>   -29.2722     0.0000     0.0000 </r>
       <r>   -29.1675     0.0000     0.0000 </r>
       <r>   -29.0627     0.0000     0.0000 </r>
       <r>   -28.9579     0.0001     0.0000 </r>
       <r>   -28.8531     0.0022     0.0002 </r>
       <r>   -28.7483     0.0206     0.0024 </r>
       <r>   -28.6435     0.0645     0.0092 </r>
       <r>   -28.5387    -0.1580    -0.0074 </r>
       <r>   -28.4339    -0.8181    -0.0931 </r>
       <r>   -28.3291     1.3903     0.0526 </r>
       <r>   -28.2243     8.1416     0.9057 </r>
       <r>   -28.1195     9.0449     1.8536 </r>
       <r>   -28.0147     2.3701     2.1020 </r>
       <r>   -27.9099    -0.8010     2.0180 </r>
       <r>   -27.8051    -0.2657     1.9902 </r>
       <r>   -27.7003     0.0625     1.9967 </r>
       <r>   -27.5956     0.0276     1.9996 </r>
       <r>   -27.4908     0.0034     2.0000 </r>
       <r>   -27.3860     0.0002     2.0000 </r>
       <r>   -27.2812     0.0000     2.0000 </r>
       <r>   -27.1764     0.0000     2.0000 </r>
       <r>   -27.0716     0.0000     2.0000 </r>
       <r>   -26.9668     0.0000     2.0000 </r>
       <r>   -26.8620     0.0000     2.0000 </r>
       <r>   -26.7572     0.0000     2.0000 </r>
       <r>   -26.6524     0.0000     2.0000 </r>
       <r>   -26.5476     0.0000     2.0000 </r>
       <r>   -26.4428     0.0000     2.0000 </r>
       <r>   -26.3380     0.0000     2.0000 </r>
       <r>   -26.2332     0.0000     2.0000 </r>
       <r>   -26.1284     0.0000     2.0000 </r>
       <r>   -26.0237     0.0000     2.0000 </r>
       <r>   -25.9189     0.0000     2.0000 </r>
       <r>   -25.8141     0.0000     2.0000 </r>
       <r>   -25.7093     0.0000     2.0000 </r>
       <r>   -25.6045     0.0000     2.0000 </r>
       <r>   -25.4997     0.0000     2.0000 </r>
       <r>   -25.3949     0.0000     2.0000 </r>
       <r>   -25.2901     0.0000     2.0000 </r>
       <r>   -25.1853     0.0000     2.0000 </r>
       <r>   -25.0805     0.0000     2.0000 </r>
       <r>   -24.9757     0.0000     2.0000 </r>
       <r>   -24.8709     0.0000     2.0000 </r>
       <r>   -24.7661     0.0000     2.0000 </r>
       <r>   -24.6613     0.0000     2.0000 </r>
       <r>   -24.5565     0.0000     2.0000 </r>
       <r>   -24.4517     0.0000     2.0000 </r>
       <r>   -24.3470     0.0000     2.0000 </r>
       <r>   -24.2422     0.0000     2.0000 </r>
       <r>   -24.1374     0.0000     2.0000 </r>
       <r>   -24.0326     0.0000     2.0000 </r>
       <r>   -23.9278     0.0000     2.0000 </r>
       <r>   -23.8230     0.0000     2.0000 </r>
       <r>   -23.7182     0.0000     2.0000 </r>
       <r>   -23.6134     0.0000     2.0000 </r>
       <r>   -23.5086     0.0000     2.0000 </r>
       <r>   -23.4038     0.0000     2.0000 </r>
       <r>   -23.2990     0.0000     2.0000 </r>
       <r>   -23.1942     0.0000     2.0000 </r>
       <r>   -23.0894     0.0000     2.0000 </r>
       <r>   -22.9846     0.0000     2.0000 </r>
       <r>   -22.8798     0.0000     2.0000 </r>
       <r>   -22.7751     0.0000     2.0000 </r>
       <r>   -22.6703     0.0000     2.0000 </r>
       <r>   -22.5655     0.0000     2.0000 </r>
       <r>   -22.4607     0.0000     2.0000 </r>
       <r>   -22.3559     0.0000     2.0000 </r>
       <r>   -22.2511     0.0000     2.0000 </r>
       <r>   -22.1463     0.0000     2.0000 </r>
       <r>   -22.0415     0.0000     2.0000 </r>
       <r>   -21.9367     0.0000     2.0000 </r>
       <r>   -21.8319     0.0000     2.0000 </r>
       <r>   -21.7271     0.0000     2.0000 </r>
       <r>   -21.6223     0.0000     2.0000 </r>
       <r>   -21.5175     0.0000     2.0000 </r>
       <r>   -21.4127     0.0000     2.0000 </r>
       <r>   -21.3079     0.0000     2.0000 </r>
       <r>   -21.2032     0.0000     2.0000 </r>
       <r>   -21.0984     0.0000     2.0000 </r>
       <r>   -20.9936     0.0000     2.0000 </r>
       <r>   -20.8888     0.0000     2.0000 </r>
       <r>   -20.7840     0.0000     2.0000 </r>
       <r>   -20.6792     0.0000     2.0000 </r>
       <r>   -20.5744     0.0000     2.0000 </r>
       <r>   -20.4696     0.0000     2.0000 </r>
       <r>   -20.3648     0.0000     2.0000 </r>
       <r>   -20.2600     0.0000     2.0000 </r>
       <r>   -20.1552     0.0000     2.0000 </r>
       <r>   -20.0504     0.0000     2.0000 </r>
       <r>   -19.9456     0.0000     2.0000 </r>
       <r>   -19.8408     0.0000     2.0000 </r>
       <r>   -19.7360     0.0000     2.0000 </r>
       <r>   -19.6312     0.0000     2.0000 </r>
       <r>   -19.5265     0.0000     2.0000 </r>
       <r>   -19.4217     0.0000     2.0000 </r>
       <r>   -19.3169     0.0000     2.0000 </r>
       <r>   -19.2121     0.0000     2.0000 </r>
       <r>   -19.1073     0.0000     2.0000 </r>
       <r>   -19.0025     0.0000     2.0000 </r>
       <r>   -18.8977     0.0000     2.0000 </r>
       <r>   -18.7929     0.0000     2.0000 </r>
       <r>   -18.6881     0.0000     2.0000 </r>
       <r>   -18.5833     0.0000     2.0000 </r>
       <r>   -18.4785     0.0000     2.0000 </r>
       <r>   -18.3737     0.0000     2.0000 </r>
       <r>   -18.2689     0.0000     2.0000 </r>
       <r>   -18.1641     0.0000     2.0000 </r>
       <r>   -18.0593     0.0000     2.0000 </r>
       <r>   -17.9546     0.0000     2.0000 </r>
       <r>   -17.8498     0.0000     2.0000 </r>
       <r>   -17.7450     0.0000     2.0000 </r>
       <r>   -17.6402     0.0000     2.0000 </r>
       <r>   -17.5354     0.0000     2.0000 </r>
       <r>   -17.4306     0.0000     2.0000 </r>
       <r>   -17.3258     0.0000     2.0000 </r>
       <r>   -17.2210     0.0000     2.0000 </r>
       <r>   -17.1162     0.0000     2.0000 </r>
       <r>   -17.0114     0.0000     2.0000 </r>
       <r>   -16.9066     0.0000     2.0000 </r>
       <r>   -16.8018     0.0000     2.0000 </r>
       <r>   -16.6970     0.0000     2.0000 </r>
       <r>   -16.5922     0.0000     2.0000 </r>
       <r>   -16.4874     0.0000     2.0000 </r>
       <r>   -16.3827     0.0000     2.0000 </r>
       <r>   -16.2779     0.0000     2.0000 </r>
       <r>   -16.1731     0.0000     2.0000 </r>
       <r>   -16.0683     0.0000     2.0000 </r>
       <r>   -15.9635     0.0000     2.0000 </r>
       <r>   -15.8587     0.0000     2.0000 </r>
       <r>   -15.7539     0.0000     2.0000 </r>
       <r>   -15.6491     0.0000     2.0000 </r>
       <r>   -15.5443     0.0000     2.0000 </r>
       <r>   -15.4395     0.0000     2.0000 </r>
       <r>   -15.3347     0.0000     2.0000 </r>
       <r>   -15.2299     0.0000     2.0000 </r>
       <r>   -15.1251     0.0000     2.0000 </r>
       <r>   -15.0203     0.0000     2.0000 </r>
       <r>   -14.9155     0.0000     2.0000 </r>
       <r>   -14.8107     0.0000     2.0000 </r>
       <r>   -14.7060     0.0000     2.0000 </r>
       <r>   -14.6012     0.0000     2.0000 </r>
       <r>   -14.4964     0.0001     2.0000 </r>
       <r>   -14.3916     0.0013     2.0001 </r>
       <r>   -14.2868     0.0143     2.0016 </r>
       <r>   -14.1820     0.0594     2.0079 </r>
       <r>   -14.0772    -0.0636     2.0012 </r>
       <r>   -13.9724    -0.7433     1.9233 </r>
       <r>   -13.8676     0.4975     1.9754 </r>
       <r>   -13.7628     6.8824     2.6967 </r>
       <r>   -13.6580     9.7432     3.7177 </r>
       <r>   -13.5532     3.6570     4.1009 </r>
       <r>   -13.4484    -0.6438     4.0335 </r>
       <r>   -13.3436    -0.4102     3.9905 </r>
       <r>   -13.2388     0.0482     3.9955 </r>
       <r>   -13.1341     0.0370     3.9994 </r>
       <r>   -13.0293     0.0054     4.0000 </r>
       <r>   -12.9245     0.0003     4.0000 </r>
       <r>   -12.8197     0.0000     4.0000 </r>
       <r>   -12.7149     0.0000     4.0000 </r>
       <r>   -12.6101     0.0000     4.0000 </r>
       <r>   -12.5053     0.0000     4.0000 </r>
       <r>   -12.4005     0.0000     4.0000 </r>
       <r>   -12.2957     0.0009     4.0001 </r>
       <r>   -12.1909     0.0114     4.0013 </r>
       <r>   -12.0861     0.0546     4.0070 </r>
       <r>   -11.9813    -0.0234     4.0046 </r>
       <r>   -11.8765    -0.6729     3.9340 </r>
       <r>   -11.7717     0.1033     3.9449 </r>
       <r>   -11.6669     6.1160     4.5858 </r>
       <r>   -11.5622    10.0163     5.6354 </r>
       <r>   -11.4574     4.3899     6.0955 </r>
       <r>   -11.3526    -1.1958     5.9702 </r>
       <r>   -11.2478    -0.1190     5.9577 </r>
       <r>   -11.1430     6.7330     6.6633 </r>
       <r>   -11.0382     9.8424     7.6947 </r>
       <r>   -10.9334     3.2271     8.0329 </r>
       <r>   -10.8286    -0.4863     7.9819 </r>
       <r>   -10.7238     5.6862     8.5778 </r>
       <r>   -10.6190     9.9984     9.6255 </r>
       <r>   -10.5142     4.4583    10.0927 </r>
       <r>   -10.4094    -0.4729    10.0432 </r>
       <r>   -10.3046    -0.4951     9.9913 </r>
       <r>   -10.1998     0.0329     9.9948 </r>
       <r>   -10.0950     0.0427     9.9992 </r>
       <r>    -9.9902     0.0069     9.9999 </r>
       <r>    -9.8855     0.0005    10.0000 </r>
       <r>    -9.7807     0.0000    10.0000 </r>
       <r>    -9.6759     0.0000    10.0000 </r>
       <r>    -9.5711     0.0000    10.0000 </r>
       <r>    -9.4663     0.0000    10.0000 </r>
       <r>    -9.3615     0.0000    10.0000 </r>
       <r>    -9.2567     0.0000    10.0000 </r>
       <r>    -9.1519     0.0000    10.0000 </r>
       <r>    -9.0471     0.0000    10.0000 </r>
       <r>    -8.9423     0.0000    10.0000 </r>
       <r>    -8.8375     0.0000    10.0000 </r>
       <r>    -8.7327     0.0000    10.0000 </r>
       <r>    -8.6279     0.0000    10.0000 </r>
       <r>    -8.5231     0.0000    10.0000 </r>
       <r>    -8.4183     0.0000    10.0000 </r>
       <r>    -8.3136     0.0000    10.0000 </r>
       <r>    -8.2088     0.0000    10.0000 </r>
       <r>    -8.1040     0.0000    10.0000 </r>
       <r>    -7.9992     0.0000    10.0000 </r>
       <r>    -7.8944     0.0000    10.0000 </r>
       <r>    -7.7896     0.0000    10.0000 </r>
       <r>    -7.6848     0.0001    10.0000 </r>
       <r>    -7.5800     0.0016    10.0002 </r>
       <r>    -7.4752     0.0168    10.0019 </r>
       <r>    -7.3704     0.0628    10.0085 </r>
       <r>    -7.2656    -0.0912     9.9990 </r>
       <r>    -7.1608    -0.7241     9.9231 </r>
       <r>    -7.0560     0.9438    10.0220 </r>
       <r>    -6.9512     6.8311    10.7378 </r>
       <r>    -6.8464     8.1799    11.5950 </r>
       <r>    -6.7417     8.4912    12.4848 </r>
       <r>    -6.6369    17.1190    14.2788 </r>
       <r>    -6.5321    15.3497    15.8873 </r>
       <r>    -6.4273     1.5599    16.0508 </r>
       <r>    -6.3225    -3.0655    15.7296 </r>
       <r>    -6.2177    12.5021    17.0397 </r>
       <r>    -6.1129    35.0478    20.7125 </r>
       <r>    -6.0081    36.4022    24.5272 </r>
       <r>    -5.9033    28.8013    27.5454 </r>
       <r>    -5.7985    35.9257    31.3102 </r>
       <r>    -5.6937    69.0362    38.5447 </r>
       <r>    -5.5889   156.6583    54.9615 </r>
       <r>    -5.4841   269.0170    83.1527 </r>
       <r>    -5.3793   294.2385   113.9870 </r>
       <r>    -5.2745   235.6802   138.6847 </r>
       <r>    -5.1697   220.5354   161.7954 </r>
       <r>    -5.0650   292.4101   192.4381 </r>
       <r>    -4.9602   358.7663   230.0344 </r>
       <r>    -4.8554   329.2111   264.5336 </r>
       <r>    -4.7506   294.4722   295.3924 </r>
       <r>    -4.6458   355.2951   332.6250 </r>
       <r>    -4.5410   412.0239   375.8024 </r>
       <r>    -4.4362   419.0827   419.7195 </r>
       <r>    -4.3314   496.1859   471.7166 </r>
       <r>    -4.2266   552.4850   529.6134 </r>
       <r>    -4.1218   373.1352   568.7156 </r>
       <r>    -4.0170   110.9544   580.3428 </r>
       <r>    -3.9122    12.0537   581.6060 </r>
       <r>    -3.8074    21.5100   583.8601 </r>
       <r>    -3.7026    22.0631   586.1722 </r>
       <r>    -3.5978    16.5541   587.9069 </r>
       <r>    -3.4931    23.4383   590.3631 </r>
       <r>    -3.3883    23.1432   592.7884 </r>
       <r>    -3.2835     7.5998   593.5848 </r>
       <r>    -3.1787     4.9877   594.1075 </r>
       <r>    -3.0739    38.1809   598.1086 </r>
       <r>    -2.9691    60.9213   604.4927 </r>
       <r>    -2.8643    35.0530   608.1661 </r>
       <r>    -2.7595     8.4802   609.0547 </r>
       <r>    -2.6547     8.2525   609.9195 </r>
       <r>    -2.5499    17.3784   611.7407 </r>
       <r>    -2.4451    21.6127   614.0056 </r>
       <r>    -2.3403    18.8317   615.9790 </r>
       <r>    -2.2355    16.9351   617.7537 </r>
       <r>    -2.1307    27.5607   620.6419 </r>
       <r>    -2.0259    41.3249   624.9724 </r>
       <r>    -1.9212    39.3423   629.0953 </r>
       <r>    -1.8164    34.5404   632.7149 </r>
       <r>    -1.7116    38.1617   636.7140 </r>
       <r>    -1.6068    39.5109   640.8545 </r>
       <r>    -1.5020    26.1442   643.5942 </r>
       <r>    -1.3972    14.3683   645.0999 </r>
       <r>    -1.2924    20.2787   647.2250 </r>
       <r>    -1.1876    26.2410   649.9749 </r>
       <r>    -1.0828    31.4672   653.2724 </r>
       <r>    -0.9780    56.0056   659.1414 </r>
       <r>    -0.8732    69.5251   666.4272 </r>
       <r>    -0.7684    44.1966   671.0587 </r>
       <r>    -0.6636    11.5744   672.2717 </r>
       <r>    -0.5588    -1.5959   672.1044 </r>
       <r>    -0.4540    -1.3137   671.9667 </r>
       <r>    -0.3492     0.1156   671.9789 </r>
       <r>    -0.2445     0.1649   671.9961 </r>
       <r>    -0.1397     0.0337   671.9997 </r>
       <r>    -0.0349     0.0030   672.0000 </r>
       <r>     0.0699     0.0001   672.0000 </r>
       <r>     0.1747     0.0000   672.0000 </r>
       <r>     0.2795     0.0000   672.0000 </r>
       <r>     0.3843     0.0000   672.0000 </r>
       <r>     0.4891     0.0000   672.0000 </r>
       <r>     0.5939     0.0000   672.0000 </r>
       <r>     0.6987     0.0000   672.0000 </r>
       <r>     0.8035     0.0000   672.0000 </r>
       <r>     0.9083     0.0000   672.0000 </r>
       <r>     1.0131     0.0000   672.0000 </r>
       <r>     1.1179     0.0000   672.0000 </r>
       <r>     1.2227     0.0000   672.0000 </r>
      </set>
     </set>
    </array>
   </total>
  </dos>
 </calculation>
 <structure name="finalpos" >
  <crystal>
   <varray name="basis" >
    <v>      30.00000000       0.00000000       0.00000000 </v>
    <v>       0.00000000      30.00000000       0.00000000 </v>
    <v>       0.00000000       0.00000000      30.00000000 </v>
   </varray>
   <i name="volume">  27000.00000000 </i>
   <varray name="rec_basis" >
    <v>       0.03333333       0.00000000       0.00000000 </v>
    <v>       0.00000000       0.03333333       0.00000000 </v>
    <v>       0.00000000       0.00000000       0.03333333 </v>
   </varray>
  </crystal>
  <varray name="positions" >
   <v>       0.44576020       0.32826710       0.41691983 </v>
   <v>       0.67173288       0.55423978       0.41691983 </v>
   <v>       0.55423980       0.32826710       0.41691983 </v>
   <v>       0.32826712       0.55423978       0.41691983 </v>
   <v>       0.50000000       0.38250690       0.34021317 </v>
   <v>       0.50000000       0.38250690       0.65978680 </v>
   <v>       0.50000000       0.27609440       0.50000000 </v>
   <v>       0.27609443       0.49999998       0.50000000 </v>
   <v>       0.72390557       0.49999998       0.50000000 </v>
   <v>       0.50000000       0.72390555       0.50000000 </v>
   <v>       0.61195280       0.38804720       0.34167483 </v>
   <v>       0.61195280       0.38804720       0.65832513 </v>
   <v>       0.38804722       0.61195278       0.34167483 </v>
   <v>       0.38804722       0.61195278       0.65832513 </v>
   <v>       0.38804720       0.38804720       0.34167483 </v>
   <v>       0.38804720       0.38804720       0.65832513 </v>
   <v>       0.61195278       0.61195278       0.34167483 </v>
   <v>       0.61195278       0.61195278       0.65832513 </v>
   <v>       0.44576020       0.32826710       0.58308023 </v>
   <v>       0.67173288       0.55423978       0.58308023 </v>
   <v>       0.55791699       0.44208301       0.41809300 </v>
   <v>       0.32826705       0.44576024       0.41691983 </v>
   <v>       0.55423973       0.67173293       0.41691983 </v>
   <v>       0.55423980       0.32826710       0.58308023 </v>
   <v>       0.32826712       0.55423978       0.58308023 </v>
   <v>       0.67173295       0.44576024       0.41691983 </v>
   <v>       0.44576027       0.67173293       0.41691983 </v>
   <v>       0.44208301       0.44208301       0.41809300 </v>
   <v>       0.50000000       0.38416601       0.50000000 </v>
   <v>       0.61749315       0.50000005       0.34021317 </v>
   <v>       0.61749315       0.50000005       0.65978680 </v>
   <v>       0.38250685       0.50000005       0.34021317 </v>
   <v>       0.38250685       0.50000005       0.65978680 </v>
   <v>       0.38317830       0.38317830       0.50000000 </v>
   <v>       0.61682172       0.61682172       0.50000000 </v>
   <v>       0.61682170       0.38317830       0.50000000 </v>
   <v>       0.38317828       0.61682172       0.50000000 </v>
   <v>       0.50000000       0.50000000       0.33478917 </v>
   <v>       0.50000000       0.50000000       0.66521087 </v>
   <v>       0.32826705       0.44576024       0.58308023 </v>
   <v>       0.55423973       0.67173293       0.58308023 </v>
   <v>       0.55791699       0.44208301       0.58190703 </v>
   <v>       0.44208298       0.55791702       0.41809300 </v>
   <v>       0.44208301       0.44208301       0.58190703 </v>
   <v>       0.67173295       0.44576024       0.58308023 </v>
   <v>       0.44576027       0.67173293       0.58308023 </v>
   <v>       0.55791702       0.55791702       0.41809300 </v>
   <v>       0.38416599       0.50000002       0.50000000 </v>
   <v>       0.61583401       0.50000002       0.50000000 </v>
   <v>       0.50000000       0.61749319       0.34021317 </v>
   <v>       0.50000000       0.61749319       0.65978680 </v>
   <v>       0.50000000       0.50000000       0.50000000 </v>
   <v>       0.44208298       0.55791702       0.58190703 </v>
   <v>       0.55791702       0.55791702       0.58190703 </v>
   <v>       0.50000000       0.61583404       0.50000000 </v>
   <v>       0.26979247       0.46353870       0.54067847 </v>
   <v>       0.23320840       0.45774437       0.54714300 </v>
  </varray>
  <varray name="selective"  type="logical" >
   <v type="logical" >  F  F  F </v>
   <v type="logical" >  F  F  F </v>
   <v type="logical" >  F  F  F </v>
   <v type="logical" >  F  F  F </v>
   <v type="logical" >  F  F  F </v>
   <v type="logical" >  F  F  F </v>
   <v type="logical" >  F  F  F </v>
   <v type="logical" >  F  F  F </v>
   <v type="logical" >  F  F  F </v>
   <v type="logical" >  F  F  F </v>
   <v type="logical" >  F  F  F </v>
   <v type="logical" >  F  F  F </v>
   <v type="logical" >  F  F  F </v>
   <v type="logical" >  F  F  F </v>
   <v type="logical" >  F  F  F </v>
   <v type="logical" >  F  F  F </v>
   <v type="logical" >  F  F  F </v>
   <v type="logical" >  F  F  F </v>
   <v type="logical" >  F  F  F </v>
   <v type="logical" >  F  F  F </v>
   <v type="logical" >  F  F  F </v>
   <v type="logical" >  F  F  F </v>
   <v type="logical" >  F  F  F </v>
   <v type="logical" >  F  F  F </v>
   <v type="logical" >  F  F  F </v>
   <v type="logical" >  F  F  F </v>
   <v type="logical" >  F  F  F </v>
   <v type="logical" >  F  F  F </v>
   <v type="logical" >  F  F  F </v>
   <v type="logical" >  F  F  F </v>
   <v type="logical" >  F  F  F </v>
   <v type="logical" >  F  F  F </v>
   <v type="logical" >  F  F  F </v>
   <v type="logical" >  F  F  F </v>
   <v type="logical" >  F  F  F </v>
   <v type="logical" >  F  F  F </v>
   <v type="logical" >  F  F  F </v>
   <v type="logical" >  F  F  F </v>
   <v type="logical" >  F  F  F </v>
   <v type="logical" >  F  F  F </v>
   <v type="logical" >  F  F  F </v>
   <v type="logical" >  F  F  F </v>
   <v type="logical" >  F  F  F </v>
   <v type="logical" >  F  F  F </v>
   <v type="logical" >  F  F  F </v>
   <v type="logical" >  F  F  F </v>
   <v type="logical" >  F  F  F </v>
   <v type="logical" >  F  F  F </v>
   <v type="logical" >  F  F  F </v>
   <v type="logical" >  F  F  F </v>
   <v type="logical" >  F  F  F </v>
   <v type="logical" >  F  F  F </v>
   <v type="logical" >  F  F  F </v>
   <v type="logical" >  F  F  F </v>
   <v type="logical" >  F  F  F </v>
   <v type="logical" >  F  F  F </v>
   <v type="logical" >  F  F  F </v>
  </varray>
  <nose>
   <v>      -3.00000000       0.00000000       0.00010000       0.00010000 </v>
  </nose>
 </structure>
</modeling>
